Workbook
Name INFRA: FRE!$O$189
Name MCMV: FRE!$A$12
Name módulo: FRE!$F$32
Name programa: FRE!$E$4

Sheet Instruções
B2: FRE
B4: O Programa deverá ser o primeiro item do formulário a ser preenchido, haja vista que a estrutura do formulário pode ser alterada de acordo com o programa.
B5: O formulário é auto-explicativo com comentários em algumas células, que detalham sua forma de preenchimento.
B6: Caso necessário podem ser inseridas linhas nas tabelas de tipologias, com o cuidado de manter a formatação e as formulas.
B8: Planilhas Orçamentárias
B10: Para apresentação dos custos de habitação devem ser preenchidas as planilhas Orç_analítio_Hab, sendo permitido em alguns programas inserção da infra-estrutura juntamente com a habitação.
B11: O preenchimento da planilha Orç_sintético_Hab será automático e representa o orçamento sintético da habitação (com ou sem infra inclusa).
B12: O Orç_sintético_Hab poderá ser preenchido diretamente (sem necessidade de preencher a planilha Orç_analítico_Hab), sendo obrigatório nesses casos o preenchimento manual dos itens referentes ao "Custo direto", "BDI" e "Custo global" na linha 99 da aba "FRE".
B13: Caso a infra seja orçada em separado deve ser preenchido o Orç_eventos_Infra, onde é permitida a inserção de linhas desde que mantida a estrutura analítica do orçamento, com o cuidado de manter a formatação e formulas de soma.
B14: No Caso do financiamento à produção de lotes urbanizados - PRODULOTE - deve ser preenchido apenas o Orç_eventos_Infra.
B15: O preenchimento da planilha Orç_analítico_Equipamento_Faixa_I é necessário apenas no produtos MCMV (FAR ou FDS).
B16: Para os demais programas caso haja equipamentos condominiais estes deve ser incluídos no orçamento da habitação ou infra.
... B31: A coluna "Infra não incidente" é uma previsão da construtora para as infraestruturas necessárias para a entrega do empreendimento, mas que seus custos não são incidentes no contrato. É um cronograma informativo para registrar quando estas obras serão realizadas.

Sheet FRE
A1: (escolha) | N1: Grau de sigilo
A2: Apoio à Produção de Imóveis - Pessoa Jurídica | F2: FRE - Ficha Resumo do Empreendimento - Habitação | N2: #EXTERNO.CONFIDENCIAL
A3: PEC / MGE
A4: PEC / MPE | D4: Programa: | E4: Apoio à Produção de Imóveis - Pessoa Jurídica
A5: Alocação de Recursos em Construção
A6: Produção de Lotes Urbanizados - PRODULOTE - PJ | B6: Nome do Empreendimento
A7: PCVA - Recursos FAR | B7: {NOME DO EMPRRENDIMENTO}
A8: PCVA Entidades - Recursos FDS
A9: Outro | B9: Endereço do Empreendimento (conforme Matrícula) | M9: Complemento
B10: {RUA} | M10: {COMPLEMENTO}
B12: Bairro | I12: Município | M12: UF | N12: CEP
B13: {SETOR} | I13: {CIDADE} | M13: GO | N13: {CEP}
B15: Proponente | M15: CNPJ/CPF
B16: {PROPONENTE} | M16: {DOC. PROPONENTE}
B18: Construtora | M18: CNPJ/CPF
B19: {CONSTRUTORA} | M19: {DOC. CONSTRUTORA}
B21: Responsável técnico | J21: CAU/CREA | M21: CPF/CNPJ
B22: {RESPONSÁVEL TÉCNICO} | J22: {CREA} | M22: {DOC. RESPONSÁVEL}
B24: Incorporador (conforme Memorial de Incorporação ou RI) | M24: CPF/CNPJ
B25: {INCORPORADOR} | M25: {DOC. INCORPORADOR}
B27: Nome para contato | J27: Telefone | M27: E-mail
B28: {RESPONSÁVEL TÉCNICO} | J28: {TEL. CONTATO} | M28: {EMAIL}
E30: Este laudo refere-se a um módulo? | F30: não | I30: Número do módulo:
E34: Tipo do empreendimento: | F34: condomínio
D36: Casas | E36: {Nº DE UNIDADES} | F36: unidades | I36: Unidades comerciais | K36: unidades | M36: Tipos de UH diferentes
D38: Apartamentos | F38: unidades | I38: UHs não financiáveis | K38: unidades | M38: Nº de blocos de apartamentos
B40: Descrição do empreendimento (tipologias, blocos, equipamentos de uso comum, lazer e infraestrutura):
A41: (escolha) | B41: CONDOMÍNIO HORIZONTAL COMPOSTO POR {Nº UNIDADES} UNIDADES TÉRREAS COM MESMA TIPOLOGIA, CONTENDO CADA UMA, 3 QUARTOS SENDO UM SUITE, BANHEIRO SOCIAL, BANHEIRO PRIVATIVO, SALA DE ESTAR, COZINHA, ÁREA DE SERVIÇO E GARAGEM DESCOBERTA, CONTARÁ COM PORTARIA (GUARITA/ADIMINISTRAÇÃO)(PREENCHER COM INFORMAÇÕES DO CONDOMÍNIO). UTILIZAÇÃO DE SISTEMA DE FOSSA SÉPTICA E SUMIDOURO PARA TRATAMENTO DE ESGOTO.
A42: =IF($F$47="convencional","Estrutura + vedação",IF($F$47="não convencional","Paredes de concreto moldado in loco NBR 16055",IF($F$47="inovador","Pré-moldado bloco cerâmico",""))) -> Estrutura + vedação
A43: =IF($F$47="convencional","Alvenaria estrutural",IF($F$47="inovador","Concreto leve","")) -> Alvenaria estrutural
A44: =IF($F$47="não convencional","Painéis pré-moldados de concreto alveolar NBR 16475","")
A45: =IF($F$47="não convencional","Painéis pré-moldados de concreto NBR 16475","") | E45: Padrão de acabamento: | F45: normal
A46: =IF($F$47="inovador","PVC + concreto","")
A47: =IF($F$47="inovador","Wood frame","") | E47: Processo construtivo: | F47: convencional | J47: Sistema Construtivo: | K47: Estrutura + vedação
A48: =IF($F$47="inovador","Painéis compósitos","")
A49: =IF($F$47="inovador","Bloco gesso","") | B49: GPS: | D49: Datum: | E49: SAD-69 | F49: (preferencial: SAD-69) | J49: Longitude (oeste): | K49: 49°08'4.0" | M49: Latitude: | N49: 16°40'29.2" | O49: sul
A50: =IF($F$47="inovador","Solo-cimento","")
A51: =IF($F$47="inovador","outro (especificar)","") | D51: Área total do terreno | E51: =I66 -> {ÁREA DO LOTE} | F51: =IF($O$53=0,0,E51/$E$51) -> #VALUE! | J51: Área do sistema viário | K51: 0 | L51: =IF($O$53=0,0,K51/$E$51) -> #VALUE! | N51: Área líquida do terreno
Q52: Área total equivalente do empreendimento (total da col. 38):
D53: Área de APP | E53: 0 | F53: =IF($O$53=0,0,E53/$E$51) -> #VALUE! | J53: Área de praças/áreas verdes | K53: 0 | L53: =IF($O$53=0,0,K53/$E$51) -> #VALUE! | N53: =E51-SUM(E53,E55,K51,K53,K55) -> #VALUE! | O53: =IF($N$53=0,0,N53/$E$51) -> #VALUE!
D55: Área Non Edificandi | E55: 0 | F55: =IF($O$53=0,0,E55/$E$51) -> #VALUE! | J55: Área de outros equipamentos | K55: 0 | L55: =IF($O$53=0,0,K55/$E$51) -> #VALUE!
B57: ref. ao MÓDULO | G57: Área total do terreno | I57: =IF($F$30="sim",E51*$K$172/MAX($I$67,1),0) -> 0 | J57: m² | L57: Área líquida do terreno | N57: =IF($F$30="sim",N53*$K$172/MAX($I$67,1),0) -> 0 | O57: m²
E59: % de obra executada: | F59: 0 | M59: Prazo de obras previsto no cronograma: | N59: {PRAZO PREVISTO} | O59: meses
B61: Descrição de estágio de obras e benfeitorias executadas
B62: NENHUMA OBRA EXTERNA FOI INICIALIZADA.
B66: Área total de construção do empreendimento (total da col. 37): | I66: {ÁREA DO LOTE}
B67: Área total equivalente do empreendimento (total da col. 38): | I67: {ÁREA EQUIVALENTE}
B69: Tipologia | C69: Unid. Comercial | D69: Qtidade | E69: Descrição | G69: =IF(programa=$A$6,"", "Área privativa real col. 23") -> Área privativa real col. 23 | H69: Área Priv. ou Construída Coberta Padrão | I69: =IF(programa=$A$6,"","Área privativa equivalente col. 24") -> Área privativa equivalente col. 24 | J69: =IF(programa=$A$6,"","Área total real col. 37") -> Área total real col. 37 | K69: =IF(programa=$A$6,"Área do lote","Área total equivalente col. 38") -> Área total equivalente col. 38 | L69: =IF(programa=$A$6,"","Área equiv. de divisão não proporcional col. 30") -> Área equiv. de divisão não proporcional col. 30 | M69: =IF(programa=$A$6,"","Fração Ideal") -> Fração Ideal | N69: Valor de VENDA proposto | O69: VGV
H71: col. 20
A72: Valores das unidades | B72: 1 | D72: EX | E72: CASA TÉRREA COMPOSTA POR 3 QUARTOS, SENDO UM SUITE, 1 BANHEIRO SOCIAL, 1 SALA DE ESTAR/JANTAR, 1 COZINHA, 1 ÁREA DE SERVIÇO E 1 GARAGEM DESCOBERTA | G72: 257.7 | H72: 71.97 | I72: 71.97 | J72: 257.7 | K72: 71.97 | L72: 71.97 | M72: 257.7 | N72: 350000 | O72: =N72*D72 -> #VALUE!
B73: =B72+1 -> 2 | O73: =N73*D73 -> 0
B74: =B73+1 -> 3 | O74: =N74*D74 -> 0
B75: =B74+1 -> 4 | O75: =N75*D75 -> 0
B76: =B75+1 -> 5 | O76: =N76*D76 -> 0
B77: =B76+1 -> 6 | O77: =N77*D77 -> 0
B78: =B77+1 -> 7 | O78: =N78*D78 -> 0
B79: =B78+1 -> 8 | O79: =N79*D79 -> 0
B80: =B79+1 -> 9 | O80: =N80*D80 -> 0
B81: =B80+1 -> 10 | O81: =N81*D81 -> 0
B82: =B81+1 -> 11 | O82: =N82*D82 -> 0
B83: =B82+1 -> 12 | O83: =N83*D83 -> 0
B84: =B83+1 -> 13 | O84: =N84*D84 -> 0
... B171: =B170+1 -> 100 | O171: =N171*D171 -> 0
D172: =SUM(D72:D171) -> 0 | G172: =SUMPRODUCT($D$72:$D$171,G72:G171) -> 0 | I172: =SUMPRODUCT($D$72:$D$171,I72:I171) -> 0 | J172: =SUMPRODUCT($D$72:$D$171,J72:J171) -> 0 | K172: =SUMPRODUCT($D$72:$D$171,K72:K171) -> 0 | L172: =SUMPRODUCT($D$72:$D$171,L72:L171) -> 0 | O172: =SUM(O72:O171) -> #VALUE!
B174: Áreas | D174: % Área habitacional / Área construída total: | G174: {=IFERROR(SUMPRODUCT((C72:C171="")*(D72:D171)*(J72:J171))/I66,0)} -> 0 | H174: % Área comercial / Área construída total: | L174: {=IFERROR(SUMPRODUCT((C72:C171="C")*(D72:D171)*(J72:J171))/I66,0)} -> 0
E176: Fonte de referência | F176: CUB | J176: Indique a fonte:
E178: Data base dos custos: | F178: Janeiro 2025 | I178: 2397.45 | J178: /m²
B181: =IF($F$30<>"sim","Valor proposto do terreno:","Valor proposto do terreno para o módulo:") -> Valor proposto do terreno: | E181: Aquisição | F181: {VALOR DO TERRENO} | I181: (se adquirido recentemente ou a adquirir, informar o valor da aquisição/opção)
J183: Data de aquisição:
B186: Edificações
E187: Custo direto | F187: =I178*K172 -> 0 | I187: BDI | J187: 0.3 | L187: Custo global | M187: =ROUND(F187*(1+J187),2) -> 0 | Q187: =IF(OR(programa=$A$5,programa=$A$6),0,Orç_analítico_Hab!M430) -> 0 | R187: =IF(OR(programa=$A$5,programa=$A$6),0,Orç_analítico_Hab!M431) -> 0
L188: =IF($F$34="condomínio",M187/$K$172,"") -> #DIV/0! | M188: /m² | N188: =IF($F$34="condomínio",M187/$D$172,"") -> #DIV/0! | O188: /UH
B189: Infraestrutura e urbanização | M189: A infra foi orçada na forma analítica e separada das edificações? | N189: não
E190: Custo direto | F190: 0 | I190: BDI | J190: 0 | L190: Custo global | M190: =F190*(1+J190) -> 0
N191: =IF($F$34="condomínio",M190/$D$172,"") -> #DIV/0! | O191: /UH
B192: Equipamentos comunitários
E193: Custo direto | F193: 0 | I193: BDI | J193: =IF(MCMV=0,0,Orç_analítico_Equipamen_Faixa_I!M357) -> 0 | L193: Custo global | M193: =F193*(1+J193) -> 0
N194: =IF($F$34="condomínio",M193/$D$172,"") -> #DIV/0! | O194: /UH
L195: Custo total das obras | M195: =IF(OR(N189<"0",N189="não"),SUM(M187,M193),IF(programa=$A$6,M190,SUM(M187,M193,M190))) -> 0
L196: =IF($F$34="condomínio",M195/$K$172,"") -> #DIV/0! | M196: /m² | N196: =IF($F$34="condomínio",M195/$D$172,"") -> #DIV/0! | O196: =IF(programa=$A$6,"/LOTE","/UH") -> /UH
B197: Outras despesas | Q197: CHECAGEM VALOR OUTRAS DESPESAS
F198: Legalização | G198: =0.02*$O$172 -> #VALUE! | J198: (aceitável até 2% do VGV) | Q198: =IF(G198>O172*0.02,"(excedeu limite aceitável)","(ok)") -> #VALUE!
F199: Despesas financeiras | G199: =0.05*M195 -> 0 | J199: (juros e taxas: aceitável de 0,5% a 5% de edificações + infra + equipamentos) | Q199: =IF(OR(G199<M195*0.005,G199>M195*0.05),"(fora do intervalo aceitável)","(ok)") -> (ok)
F200: Seguros (SRE e SGC/SGI) | G200: =0.005*M195 -> 0 | J200: (aceitável até 0,5% de edificações + infra + equipamentos) | Q200: =IF(G200>M195*0.005,"(excedeu limite aceitável)","(ok)") -> (ok)
F201: Despesas de comercialização | G201: =0.08*$O$172 -> #VALUE! | J201: (aceitável de 4% a 8% do VGV) | Q201: =IF(OR(G201<O172*0.04,G201>O172*0.08),"(fora do intervalo aceitável)","(ok)") -> #VALUE!
F202: Trabalho técnico social / Gestão Condominial | G202: 50 | J202: =IF(OR(programa=$A$7,programa=$A$8),"(1,5% do valor de aquisiçãos das UH + 0,5% se implantado na forma de condominio)") -> FALSE
F203: Segurança adicional | G203: 60
L204: Total de outras despesas | M204: =IF(A12=1,SUM(G198,G200:I203),SUM(G198:I201)) -> #VALUE!
L206: Custo total de empreendimento | M206: =M195+M204+F181 -> #VALUE!
L207: =IF($F$34="condomínio",M206/$K$172,"") -> #VALUE! | M207: /m² | N207: =IF($F$34="condomínio",M206/$D$172,"") -> #VALUE! | O207: /UH
B208: Custos não incidentes | G208: Valor | K208: Responsabilidade pela execução e fonte de recursos
B213: Aporte financeiro / contrapartida / CPAC | G213: Valor
L216: VGV - Valor global de vendas | M216: =O172 -> #VALUE!
B218: Observações gerais
B219: O Condomínio Residencial será enquadrado no programa minha casa minha vida, exceto faixa 1. Sistema de construção convencional, condomínio de casas seriadas, não geminadas, localizadas no município de Senador Canedo - GO.
B222: Assinatura do proponente
B223: Nome: | C223: =B16 -> {PROPONENTE}
B224: CPF: | C224: =M16 -> {DOC. PROPONENTE}
B226: Local: | C226: GOIÂNIA
B227: Data: | C227: {DATA HOJE}

Sheet Orç_sintético_Hab
A1: (escolha) | E1: Orçamento Sintético - Habitação | K1: Grau de sigilo
A2: Habitacional horizontal | G2: =FRE!$D$4 -> Programa: | H2: =FRE!$E$4 -> Apoio à Produção de Imóveis - Pessoa Jurídica | K2: #EXTERNO.CONFIDENCIAL
A3: Vertical: habit. / salas / misto
A4: Vertical andar livre
A5: Vertical parede de concreto
T20: =A2 -> Habitacional horizontal | X20: =A3 -> Vertical: habit. / salas / misto | AB20: =A4 -> Vertical andar livre | AF20: =A5 -> Vertical parede de concreto
T21: mínimo | U21: máximo infra sintética | V21: máximo infra analítica | X21: mínimo | Y21: máximo infra sintética | Z21: máximo infra analítica | AB21: mínimo | AC21: máximo infra sintética | AD21: máximo infra analítica | AF21: mínimo | AG21: máximo infra sintética | AH21: máximo infra analítica
B22: Tipologia: | C22: Habitacional horizontal | I22: =IF(FRE!$A$12=1,"sim",FRE!N189) -> não
B24: Item | C24: Serviço | K24: Incidência | L24: Custo | M24: % acumulado | O24: =IF(C22="(escolha)","(escolha a tipologia)",C22) -> Habitacional horizontal | R24: Status | AI24: incidencia calculada | AJ24: erro acumulado | AK24: Calculo Arredondamento Monetário
B25: 1 | C25: SERVIÇOS PRELIMINARES GERAIS | K25: =SUM(K26:K35) -> 0.16 | L25: =SUM(L26:L35) -> 0 | M25: =IF(SUM($L$25,$L$36,$L$39,$L$40,$L$45,$L$48,$L$55,$L$62,$L$71,$L$75)=0,0,L25/SUM($L$25,$L$36,$L$39,$L$40,$L$45,$L$48,$L$55,$L$62,$L$71,$L$75)) -> 0 | AK25: =SUM(AK26:AK35) -> 0
B26: 1.1 | C26: serviços técnicos (projetos, orçamentos, levant. topog., sondagem, licenças e PCMAT) | K26: 0.0076 | L26: =ROUND(K26*FRE!$M$187,2) -> 0 | O26: =IF($O$24=$T$20,T26,IF($O$24=$X$20,X26,IF($O$24=$AB$20,AB26,AF26))) -> 0.005 | P26: a | Q26: =IF(OR(FRE!$N$189="não",FRE!$N$189<"0"), IF($O$24=$T$20,U26,IF($O$24=$X$20,Y26,IF($O$24=$AB$20,AC26,AG26))), IF($O$24=$T$20,V26,IF($O$24=$X$20,Z26,IF($O$24=$AB$20,AD26,AH26)))) -> 0.0076 | R26: =IF(K26>Q26,"Excedeu limites",IF(K26<O26,"Abaixo do limite","ok")) -> ok | T26: 0.005 | U26: 0.0076 | V26: 0.0076 | X26: 0.005 | Y26: 0.0076 | Z26: 0.0076 | AB26: 0.005 | AC26: 0.0076 | AD26: 0.0076 | AF26: 0.005 | AG26: 0.0076 | AH26: 0.0076 | AI26: =Orç_analítico_Hab!M19/IF(Orç_analítico_Hab!M$430=0,1,Orç_analítico_Hab!M$430) -> 0 | AJ26: =AI26-ROUND(AI26,4) -> 0 | AK26: =ROUND(L26,2) -> 0
B27: 1.2 | C27: instalações e canteiros (barracão, cercamento e placa da obra) | K27: 0.019 | L27: =ROUND(K27*FRE!$M$187,2) -> 0 | O27: =IF($O$24=$T$20,T27,IF($O$24=$X$20,X27,IF($O$24=$AB$20,AB27,AF27))) -> 0.001 | P27: a | Q27: =IF(OR(FRE!$N$189="não",FRE!$N$189<"0"), IF($O$24=$T$20,U27,IF($O$24=$X$20,Y27,IF($O$24=$AB$20,AC27,AG27))), IF($O$24=$T$20,V27,IF($O$24=$X$20,Z27,IF($O$24=$AB$20,AD27,AH27)))) -> 0.019 | R27: =IF(K27>Q27,"Excedeu limites",IF(K27<O27,"Abaixo do limite","ok")) -> ok | T27: 0.001 | U27: 0.019 | V27: 0.019 | X27: 0.001 | Y27: 0.019 | Z27: 0.019 | AB27: 0.001 | AC27: 0.019 | AD27: 0.019 | AF27: 0.001 | AG27: 0.019 | AH27: 0.019 | AI27: =Orç_analítico_Hab!M20/IF(Orç_analítico_Hab!M$430=0,1,Orç_analítico_Hab!M$430) -> 0 | AJ27: =AI27-ROUND(AI27,4)+AJ26 -> 0 | AK27: =ROUND(L27,2) -> 0
B28: 1.3 | C28: ligações provisórias (água, energia, telefone e esgoto) | K28: 0.0004 | L28: =ROUND(K28*FRE!$M$187,2) -> 0 | O28: =IF($O$24=$T$20,T28,IF($O$24=$X$20,X28,IF($O$24=$AB$20,AB28,AF28))) -> 0.0001 | P28: a | Q28: =IF(OR(FRE!$N$189="não",FRE!$N$189<"0"), IF($O$24=$T$20,U28,IF($O$24=$X$20,Y28,IF($O$24=$AB$20,AC28,AG28))), IF($O$24=$T$20,V28,IF($O$24=$X$20,Z28,IF($O$24=$AB$20,AD28,AH28)))) -> 0.0004 | R28: =IF(K28>Q28,"Excedeu limites",IF(K28<O28,"Abaixo do limite","ok")) -> ok | T28: 0.0001 | U28: 0.0004 | V28: 0.0004 | X28: 0.0001 | Y28: 0.0004 | Z28: 0.0004 | AB28: 0.0001 | AC28: 0.0004 | AD28: 0.0004 | AF28: 0.0001 | AG28: 0.0004 | AH28: 0.0004 | AI28: =Orç_analítico_Hab!M21/IF(Orç_analítico_Hab!M$430=0,1,Orç_analítico_Hab!M$430) -> 0 | AJ28: =AI28-ROUND(AI28,4)+AJ27 -> 0 | AK28: =ROUND(L28,2) -> 0
B29: 1.4 | C29: manutenção canteiro/consumo | K29: 0.0143 | L29: =ROUND(K29*FRE!$M$187,2) -> 0 | O29: =IF($O$24=$T$20,T29,IF($O$24=$X$20,X29,IF($O$24=$AB$20,AB29,AF29))) -> 0.01 | P29: a | Q29: =IF(OR(FRE!$N$189="não",FRE!$N$189<"0"), IF($O$24=$T$20,U29,IF($O$24=$X$20,Y29,IF($O$24=$AB$20,AC29,AG29))), IF($O$24=$T$20,V29,IF($O$24=$X$20,Z29,IF($O$24=$AB$20,AD29,AH29)))) -> 0.0143 | R29: =IF(K29>Q29,"Excedeu limites",IF(K29<O29,"Abaixo do limite","ok")) -> ok | T29: 0.01 | U29: 0.0143 | V29: 0.0143 | X29: 0.01 | Y29: 0.0143 | Z29: 0.0143 | AB29: 0.01 | AC29: 0.0143 | AD29: 0.0143 | AF29: 0.01 | AG29: 0.0143 | AH29: 0.0143 | AI29: =Orç_analítico_Hab!M22/IF(Orç_analítico_Hab!M$430=0,1,Orç_analítico_Hab!M$430) -> 0 | AJ29: =AI29-ROUND(AI29,4)+AJ28 -> 0 | AK29: =ROUND(L29,2) -> 0
B30: 1.5 | C30: transportes máquinas e equipamentos | K30: 0.0394 | L30: =ROUND(K30*FRE!$M$187,2) -> 0 | O30: =IF($O$24=$T$20,T30,IF($O$24=$X$20,X30,IF($O$24=$AB$20,AB30,AF30))) -> 0.006 | P30: a | Q30: =IF(OR(FRE!$N$189="não",FRE!$N$189<"0"), IF($O$24=$T$20,U30,IF($O$24=$X$20,Y30,IF($O$24=$AB$20,AC30,AG30))), IF($O$24=$T$20,V30,IF($O$24=$X$20,Z30,IF($O$24=$AB$20,AD30,AH30)))) -> 0.0394 | R30: =IF(K30>Q30,"Excedeu limites",IF(K30<O30,"Abaixo do limite","ok")) -> ok | T30: 0.006 | U30: 0.0394 | V30: 0.0394 | X30: 0.006 | Y30: 0.0394 | Z30: 0.0394 | AB30: 0.006 | AC30: 0.0394 | AD30: 0.0394 | AF30: 0.006 | AG30: 0.0394 | AH30: 0.0394 | AI30: =Orç_analítico_Hab!M23/IF(Orç_analítico_Hab!M$430=0,1,Orç_analítico_Hab!M$430) -> 0 | AJ30: =AI30-ROUND(AI30,4)+AJ29 -> 0 | AK30: =ROUND(L30,2) -> 0
B31: 1.6 | C31: controle tecnológico | K31: 0.0067 | L31: =ROUND(K31*FRE!$M$187,2) -> 0 | O31: =IF($O$24=$T$20,T31,IF($O$24=$X$20,X31,IF($O$24=$AB$20,AB31,AF31))) -> 0.0005 | P31: a | Q31: =IF(OR(FRE!$N$189="não",FRE!$N$189<"0"), IF($O$24=$T$20,U31,IF($O$24=$X$20,Y31,IF($O$24=$AB$20,AC31,AG31))), IF($O$24=$T$20,V31,IF($O$24=$X$20,Z31,IF($O$24=$AB$20,AD31,AH31)))) -> 0.0067 | R31: =IF(K31>Q31,"Excedeu limites",IF(K31<O31,"Abaixo do limite","ok")) -> ok | T31: 0.0005 | U31: 0.0067 | V31: 0.0067 | X31: 0.0005 | Y31: 0.0067 | Z31: 0.0067 | AB31: 0.0005 | AC31: 0.0067 | AD31: 0.0067 | AF31: 0.0005 | AG31: 0.0067 | AH31: 0.0067 | AI31: =Orç_analítico_Hab!M24/IF(Orç_analítico_Hab!M$430=0,1,Orç_analítico_Hab!M$430) -> 0 | AJ31: =AI31-ROUND(AI31,4)+AJ30 -> 0 | AK31: =ROUND(L31,2) -> 0
B32: 1.7 | C32: gestão de resíduos | K32: 0.0011 | L32: =ROUND(K32*FRE!$M$187,2) -> 0 | O32: =IF($O$24=$T$20,T32,IF($O$24=$X$20,X32,IF($O$24=$AB$20,AB32,AF32))) -> 0.0005 | P32: a | Q32: =IF(OR(FRE!$N$189="não",FRE!$N$189<"0"), IF($O$24=$T$20,U32,IF($O$24=$X$20,Y32,IF($O$24=$AB$20,AC32,AG32))), IF($O$24=$T$20,V32,IF($O$24=$X$20,Z32,IF($O$24=$AB$20,AD32,AH32)))) -> 0.0011 | R32: =IF(K32>Q32,"Excedeu limites",IF(K32<O32,"Abaixo do limite","ok")) -> ok | T32: 0.0005 | U32: 0.0011 | V32: 0.0011 | X32: 0.0005 | Y32: 0.0011 | Z32: 0.0011 | AB32: 0.0005 | AC32: 0.0011 | AD32: 0.0011 | AF32: 0.0005 | AG32: 0.0011 | AH32: 0.0011 | AI32: =Orç_analítico_Hab!M25/IF(Orç_analítico_Hab!M$430=0,1,Orç_analítico_Hab!M$430) -> 0 | AJ32: =AI32-ROUND(AI32,4)+AJ31 -> 0 | AK32: =ROUND(L32,2) -> 0
B33: 1.8 | C33: gestão da qualidade | K33: 0.0009 | L33: =ROUND(K33*FRE!$M$187,2) -> 0 | O33: =IF($O$24=$T$20,T33,IF($O$24=$X$20,X33,IF($O$24=$AB$20,AB33,AF33))) -> 0.0005 | P33: a | Q33: =IF(OR(FRE!$N$189="não",FRE!$N$189<"0"), IF($O$24=$T$20,U33,IF($O$24=$X$20,Y33,IF($O$24=$AB$20,AC33,AG33))), IF($O$24=$T$20,V33,IF($O$24=$X$20,Z33,IF($O$24=$AB$20,AD33,AH33)))) -> 0.0009 | R33: =IF(K33>Q33,"Excedeu limites",IF(K33<O33,"Abaixo do limite","ok")) -> ok | T33: 0.0005 | U33: 0.0009 | V33: 0.0009 | X33: 0.0005 | Y33: 0.0009 | Z33: 0.0009 | AB33: 0.0005 | AC33: 0.0009 | AD33: 0.0009 | AF33: 0.0005 | AG33: 0.0009 | AH33: 0.0009 | AI33: =Orç_analítico_Hab!M26/IF(Orç_analítico_Hab!M$430=0,1,Orç_analítico_Hab!M$430) -> 0 | AJ33: =AI33-ROUND(AI33,4)+AJ32 -> 0 | AK33: =ROUND(L33,2) -> 0
B34: 1.9 | C34: equipamentos de proteção coletivos | K34: 0.0006 | L34: =ROUND(K34*FRE!$M$187,2) -> 0 | O34: =IF($O$24=$T$20,T34,IF($O$24=$X$20,X34,IF($O$24=$AB$20,AB34,AF34))) -> 0 | P34: a | Q34: =IF(OR(FRE!$N$189="não",FRE!$N$189<"0"), IF($O$24=$T$20,U34,IF($O$24=$X$20,Y34,IF($O$24=$AB$20,AC34,AG34))), IF($O$24=$T$20,V34,IF($O$24=$X$20,Z34,IF($O$24=$AB$20,AD34,AH34)))) -> 0.0006 | R34: =IF(K34>Q34,"Excedeu limites",IF(K34<O34,"Abaixo do limite","ok")) -> ok | T34: 0 | U34: 0.0006 | V34: 0.0006 | X34: 0 | Y34: 0.0006 | Z34: 0.0006 | AB34: 0 | AC34: 0.0006 | AD34: 0.0006 | AF34: 0 | AG34: 0.0006 | AH34: 0.0006 | AI34: =Orç_analítico_Hab!M27/IF(Orç_analítico_Hab!M$430=0,1,Orç_analítico_Hab!M$430) -> 0 | AJ34: =AI34-ROUND(AI34,4)+AJ33 -> 0 | AK34: =ROUND(L34,2) -> 0
B35: 1.10 | C35: administração local (engenheiros, mestres, etc.) | K35: 0.07 | L35: =ROUND(K35*FRE!$M$187,2) -> 0 | O35: =IF($O$24=$T$20,T35,IF($O$24=$X$20,X35,IF($O$24=$AB$20,AB35,AF35))) -> 0.025 | P35: a | Q35: =IF(OR(FRE!$N$189="não",FRE!$N$189<"0"), IF($O$24=$T$20,U35,IF($O$24=$X$20,Y35,IF($O$24=$AB$20,AC35,AG35))), IF($O$24=$T$20,V35,IF($O$24=$X$20,Z35,IF($O$24=$AB$20,AD35,AH35)))) -> 0.07 | R35: =IF(K35>Q35,"Excedeu limites",IF(K35<O35,"Abaixo do limite","ok")) -> ok | T35: 0.025 | U35: 0.07 | V35: 0.07 | X35: 0.025 | Y35: 0.07 | Z35: 0.07 | AB35: 0.025 | AC35: 0.07 | AD35: 0.07 | AF35: 0.025 | AG35: 0.07 | AH35: 0.07 | AI35: =Orç_analítico_Hab!M28/IF(Orç_analítico_Hab!M$430=0,1,Orç_analítico_Hab!M$430) -> 0 | AJ35: =AI35-ROUND(AI35,4)+AJ34 -> 0 | AK35: =ROUND(L35,2) -> 0
B36: 2 | C36: FUNDAÇÕES E CONTENÇÕES | K36: =SUM(K37:K38) -> 0.11 | L36: =SUM(L37:L38) -> 0 | M36: =IF(SUM($L$25,$L$36,$L$39,$L$40,$L$45,$L$48,$L$55,$L$62,$L$71,$L$75)=0,0,M25+L36/SUM($L$25,$L$36,$L$39,$L$40,$L$45,$L$48,$L$55,$L$62,$L$71,$L$75)) -> 0 | AK36: =SUM(AK37:AK38) -> 0
B37: 2.1 | C37: Fundações | K37: 0.08 | L37: =ROUND(K37*FRE!$M$187,2) -> 0 | O37: =IF($O$24=$T$20,T37,IF($O$24=$X$20,X37,IF($O$24=$AB$20,AB37,AF37))) -> 0.03 | P37: a | Q37: =IF(OR(FRE!$N$189="não",FRE!$N$189<"0"), IF($O$24=$T$20,U37,IF($O$24=$X$20,Y37,IF($O$24=$AB$20,AC37,AG37))), IF($O$24=$T$20,V37,IF($O$24=$X$20,Z37,IF($O$24=$AB$20,AD37,AH37)))) -> 0.08 | R37: =IF(K37>Q37,"Excedeu limites",IF(K37<O37,"Abaixo do limite","ok")) -> ok | T37: 0.03 | U37: 0.08 | V37: 0.095 | X37: 0.03 | Y37: 0.08 | Z37: 0.095 | AB37: 0.03 | AC37: 0.07 | AD37: 0.085 | AF37: 0.03 | AG37: 0.08 | AH37: 0.095 | AI37: =SUM(Orç_analítico_Hab!M33:'Orç_analítico_Hab'!M52)/IF(Orç_analítico_Hab!M$430=0,1,Orç_analítico_Hab!M$430) -> 0 | AJ37: =AI37-ROUND(AI37,4)+AJ35 -> 0 | AK37: =ROUND(L37,2) -> 0
B38: 2.2 | C38: Contenções/arrimos especiais | K38: 0.03 | L38: =ROUND(K38*FRE!$M$187,2) -> 0 | O38: =IF($O$24=$T$20,T38,IF($O$24=$X$20,X38,IF($O$24=$AB$20,AB38,AF38))) -> 0 | P38: a | Q38: =IF(OR(FRE!$N$189="não",FRE!$N$189<"0"), IF($O$24=$T$20,U38,IF($O$24=$X$20,Y38,IF($O$24=$AB$20,AC38,AG38))), IF($O$24=$T$20,V38,IF($O$24=$X$20,Z38,IF($O$24=$AB$20,AD38,AH38)))) -> 0.03 | R38: =IF(K38>Q38,"Excedeu limites",IF(K38<O38,"Abaixo do limite","ok")) -> ok | T38: 0 | U38: 0.03 | V38: 0.035 | X38: 0 | Y38: 0.03 | Z38: 0.035 | AB38: 0 | AC38: 0.03 | AD38: 0.035 | AF38: 0 | AG38: 0.03 | AH38: 0.035 | AI38: =SUM(Orç_analítico_Hab!M55:'Orç_analítico_Hab'!M61)/IF(Orç_analítico_Hab!M$430=0,1,Orç_analítico_Hab!M$430) -> 0 | AJ38: =AI38-ROUND(AI38,4)+AJ37 -> 0 | AK38: =ROUND(L38,2) -> 0
B39: 3 | C39: SUPRAESTRUTURA | K39: =ROUND(AI39,4) -> 0 | L39: =ROUND(K39*FRE!$M$187,2) -> 0 | M39: =IF(SUM($L$25,$L$36,$L$39,$L$40,$L$45,$L$48,$L$55,$L$62,$L$71,$L$75)=0,0,M36+L39/SUM($L$25,$L$36,$L$39,$L$40,$L$45,$L$48,$L$55,$L$62,$L$71,$L$75)) -> 0 | O39: =IF($O$24=$T$20,T39,IF($O$24=$X$20,X39,IF($O$24=$AB$20,AB39,AF39))) -> 0.03 | P39: a | Q39: =IF(OR(FRE!$N$189="não",FRE!$N$189<"0"), IF($O$24=$T$20,U39,IF($O$24=$X$20,Y39,IF($O$24=$AB$20,AC39,AG39))), IF($O$24=$T$20,V39,IF($O$24=$X$20,Z39,IF($O$24=$AB$20,AD39,AH39)))) -> 0.15 | R39: =IF(K39>Q39,"Excedeu limites",IF(K39<O39,"Abaixo do limite","ok")) -> Abaixo do limite | T39: 0.03 | U39: 0.15 | V39: 0.175 | X39: 0.1 | Y39: 0.25 | Z39: 0.3 | AB39: 0.1 | AC39: 0.25 | AD39: 0.3 | AF39: 0.14 | AG39: 0.35 | AH39: 0.4 | AI39: =SUM(Orç_analítico_Hab!M65:'Orç_analítico_Hab'!M69)/IF(Orç_analítico_Hab!M$430=0,1,Orç_analítico_Hab!M$430) -> 0 | AJ39: =AI39-ROUND(AI39,4)+AJ38 -> 0 | AK39: =ROUND(L39,2) -> 0
B40: 4 | C40: PAREDES E PAINÉIS | K40: =SUM(K41:K44) -> 0.14 | L40: =SUM(L41:L44) -> 0 | M40: =IF(SUM($L$25,$L$36,$L$39,$L$40,$L$45,$L$48,$L$55,$L$62,$L$71,$L$75)=0,0,M39+L40/SUM($L$25,$L$36,$L$39,$L$40,$L$45,$L$48,$L$55,$L$62,$L$71,$L$75)) -> 0 | AK40: =SUM(AK41:AK44) -> 0
B41: 4.1 | C41: alvenaria / fechamentos | K41: 0.11 | L41: =ROUND(K41*FRE!$M$187,2) -> 0 | O41: =IF($O$24=$T$20,T41,IF($O$24=$X$20,X41,IF($O$24=$AB$20,AB41,AF41))) -> 0.06 | P41: a | Q41: =IF(OR(FRE!$N$189="não",FRE!$N$189<"0"), IF($O$24=$T$20,U41,IF($O$24=$X$20,Y41,IF($O$24=$AB$20,AC41,AG41))), IF($O$24=$T$20,V41,IF($O$24=$X$20,Z41,IF($O$24=$AB$20,AD41,AH41)))) -> 0.15 | R41: =IF(K41>Q41,"Excedeu limites",IF(K41<O41,"Abaixo do limite","ok")) -> ok | T41: 0.06 | U41: 0.15 | V41: 0.175 | X41: 0.04 | Y41: 0.15 | Z41: 0.18 | AB41: 0.02 | AC41: 0.08 | AD41: 0.095 | AF41: 0 | AG41: 0.005 | AH41: 0.005 | AI41: =SUM(Orç_analítico_Hab!M74:'Orç_analítico_Hab'!M81)/IF(Orç_analítico_Hab!M$430=0,1,Orç_analítico_Hab!M$430) -> 0 | AJ41: =AI41-ROUND(AI41,4)+AJ39 -> 0 | AK41: =ROUND(L41,2) -> 0
B42: 4.2 | C42: esquadrias metálicas | K42: 0.01 | L42: =ROUND(K42*FRE!$M$187,2) -> 0 | O42: =IF($O$24=$T$20,T42,IF($O$24=$X$20,X42,IF($O$24=$AB$20,AB42,AF42))) -> 0 | P42: a | Q42: =IF(OR(FRE!$N$189="não",FRE!$N$189<"0"), IF($O$24=$T$20,U42,IF($O$24=$X$20,Y42,IF($O$24=$AB$20,AC42,AG42))), IF($O$24=$T$20,V42,IF($O$24=$X$20,Z42,IF($O$24=$AB$20,AD42,AH42)))) -> 0.08 | R42: =IF(K42>Q42,"Excedeu limites",IF(K42<O42,"Abaixo do limite","ok")) -> ok | T42: 0 | U42: 0.08 | V42: 0.095 | X42: 0 | Y42: 0.08 | Z42: 0.095 | AB42: 0.02 | AC42: 0.1 | AD42: 0.12 | AF42: 0 | AG42: 0.08 | AH42: 0.095 | AI42: =SUM(Orç_analítico_Hab!M84:'Orç_analítico_Hab'!M102)/IF(Orç_analítico_Hab!M$430=0,1,Orç_analítico_Hab!M$430) -> 0 | AJ42: =AI42-ROUND(AI42,4)+AJ41 -> 0 | AK42: =ROUND(L42,2) -> 0
B43: 4.3 | C43: esquadrias de madeira | K43: 0.01 | L43: =ROUND(K43*FRE!$M$187,2) -> 0 | O43: =IF($O$24=$T$20,T43,IF($O$24=$X$20,X43,IF($O$24=$AB$20,AB43,AF43))) -> 0.01 | P43: a | Q43: =IF(OR(FRE!$N$189="não",FRE!$N$189<"0"), IF($O$24=$T$20,U43,IF($O$24=$X$20,Y43,IF($O$24=$AB$20,AC43,AG43))), IF($O$24=$T$20,V43,IF($O$24=$X$20,Z43,IF($O$24=$AB$20,AD43,AH43)))) -> 0.06 | R43: =IF(K43>Q43,"Excedeu limites",IF(K43<O43,"Abaixo do limite","ok")) -> ok | T43: 0.01 | U43: 0.06 | V43: 0.07 | X43: 0.01 | Y43: 0.06 | Z43: 0.07 | AB43: 0 | AC43: 0.04 | AD43: 0.045 | AF43: 0.01 | AG43: 0.06 | AH43: 0.07 | AI43: =SUM(Orç_analítico_Hab!M105:'Orç_analítico_Hab'!M123)/IF(Orç_analítico_Hab!M$430=0,1,Orç_analítico_Hab!M$430) -> 0 | AJ43: =AI43-ROUND(AI43,4)+AJ42 -> 0 | AK43: =ROUND(L43,2) -> 0
B44: 4.4 | C44: vidros / esquadrias especiais | K44: 0.01 | L44: =ROUND(K44*FRE!$M$187,2) -> 0 | O44: =IF($O$24=$T$20,T44,IF($O$24=$X$20,X44,IF($O$24=$AB$20,AB44,AF44))) -> 0 | P44: a | Q44: =IF(OR(FRE!$N$189="não",FRE!$N$189<"0"), IF($O$24=$T$20,U44,IF($O$24=$X$20,Y44,IF($O$24=$AB$20,AC44,AG44))), IF($O$24=$T$20,V44,IF($O$24=$X$20,Z44,IF($O$24=$AB$20,AD44,AH44)))) -> 0.03 | R44: =IF(K44>Q44,"Excedeu limites",IF(K44<O44,"Abaixo do limite","ok")) -> ok | T44: 0 | U44: 0.03 | V44: 0.035 | X44: 0 | Y44: 0.03 | Z44: 0.035 | AB44: 0.015 | AC44: 0.05 | AD44: 0.06 | AF44: 0 | AG44: 0.03 | AH44: 0.035 | AI44: =SUM(Orç_analítico_Hab!M126:'Orç_analítico_Hab'!M132)/IF(Orç_analítico_Hab!M$430=0,1,Orç_analítico_Hab!M$430) -> 0 | AJ44: =AI44-ROUND(AI44,4)+AJ43 -> 0 | AK44: =ROUND(L44,2) -> 0
B45: 5 | C45: COBERTURA E PROTEÇÕES | K45: =SUM(K46:K47) -> 0.03 | L45: =SUM(L46:L47) -> 0 | M45: =IF(SUM($L$25,$L$36,$L$39,$L$40,$L$45,$L$48,$L$55,$L$62,$L$71,$L$75)=0,0,M40+L45/SUM($L$25,$L$36,$L$39,$L$40,$L$45,$L$48,$L$55,$L$62,$L$71,$L$75)) -> 0 | AK45: =SUM(AK46:AK47) -> 0
B46: 5.1 | C46: telhados | K46: 0.02 | L46: =ROUND(K46*FRE!$M$187,2) -> 0 | O46: =IF($O$24=$T$20,T46,IF($O$24=$X$20,X46,IF($O$24=$AB$20,AB46,AF46))) -> 0 | P46: a | Q46: =IF(OR(FRE!$N$189="não",FRE!$N$189<"0"), IF($O$24=$T$20,U46,IF($O$24=$X$20,Y46,IF($O$24=$AB$20,AC46,AG46))), IF($O$24=$T$20,V46,IF($O$24=$X$20,Z46,IF($O$24=$AB$20,AD46,AH46)))) -> 0.15 | R46: =IF(K46>Q46,"Excedeu limites",IF(K46<O46,"Abaixo do limite","ok")) -> ok | T46: 0 | U46: 0.15 | V46: 0.175 | X46: 0 | Y46: 0.03 | Z46: 0.035 | AB46: 0 | AC46: 0.03 | AD46: 0.035 | AF46: 0 | AG46: 0.08 | AH46: 0.095 | AI46: =SUM(Orç_analítico_Hab!M137:'Orç_analítico_Hab'!M141)/IF(Orç_analítico_Hab!M$430=0,1,Orç_analítico_Hab!M$430) -> 0 | AJ46: =AI46-ROUND(AI46,4)+AJ44 -> 0 | AK46: =ROUND(L46,2) -> 0
B47: 5.2 | C47: impermeabilizações | K47: 0.01 | L47: =ROUND(K47*FRE!$M$187,2) -> 0 | O47: =IF($O$24=$T$20,T47,IF($O$24=$X$20,X47,IF($O$24=$AB$20,AB47,AF47))) -> 0.005 | P47: a | Q47: =IF(OR(FRE!$N$189="não",FRE!$N$189<"0"), IF($O$24=$T$20,U47,IF($O$24=$X$20,Y47,IF($O$24=$AB$20,AC47,AG47))), IF($O$24=$T$20,V47,IF($O$24=$X$20,Z47,IF($O$24=$AB$20,AD47,AH47)))) -> 0.03 | R47: =IF(K47>Q47,"Excedeu limites",IF(K47<O47,"Abaixo do limite","ok")) -> ok | T47: 0.005 | U47: 0.03 | V47: 0.035 | X47: 0.002 | Y47: 0.025 | Z47: 0.03 | AB47: 0.002 | AC47: 0.025 | AD47: 0.03 | AF47: 0.002 | AG47: 0.025 | AH47: 0.03 | AI47: =SUM(Orç_analítico_Hab!M144:'Orç_analítico_Hab'!M159)/IF(Orç_analítico_Hab!M$430=0,1,Orç_analítico_Hab!M$430) -> 0 | AJ47: =AI47-ROUND(AI47,4)+AJ46 -> 0 | AK47: =ROUND(L47,2) -> 0
B48: 6 | C48: REVESTIMENTOS | K48: =SUM(K49:K54) -> 0.185 | L48: =SUM(L49:L54) -> 0 | M48: =IF(SUM($L$25,$L$36,$L$39,$L$40,$L$45,$L$48,$L$55,$L$62,$L$71,$L$75)=0,0,M45+L48/SUM($L$25,$L$36,$L$39,$L$40,$L$45,$L$48,$L$55,$L$62,$L$71,$L$75)) -> 0 | AK48: =SUM(AK49:AK54) -> 0
B49: 6.1 | C49: revestimentos internos | K49: 0.05 | L49: =ROUND(K49*FRE!$M$187,2) -> 0 | O49: =IF($O$24=$T$20,T49,IF($O$24=$X$20,X49,IF($O$24=$AB$20,AB49,AF49))) -> 0.04 | P49: a | Q49: =IF(OR(FRE!$N$189="não",FRE!$N$189<"0"), IF($O$24=$T$20,U49,IF($O$24=$X$20,Y49,IF($O$24=$AB$20,AC49,AG49))), IF($O$24=$T$20,V49,IF($O$24=$X$20,Z49,IF($O$24=$AB$20,AD49,AH49)))) -> 0.08 | R49: =IF(K49>Q49,"Excedeu limites",IF(K49<O49,"Abaixo do limite","ok")) -> ok | T49: 0.04 | U49: 0.08 | V49: 0.095 | X49: 0.04 | Y49: 0.08 | Z49: 0.095 | AB49: 0.01 | AC49: 0.06 | AD49: 0.07 | AF49: 0.02 | AG49: 0.08 | AH49: 0.095 | AI49: =SUM(Orç_analítico_Hab!M164:'Orç_analítico_Hab'!M171)/IF(Orç_analítico_Hab!M$430=0,1,Orç_analítico_Hab!M$430) -> 0 | AJ49: =AI49-ROUND(AI49,4)+AJ47 -> 0 | AK49: =ROUND(L49,2) -> 0
B50: 6.2 | C50: azulejos | K50: 0.03 | L50: =ROUND(K50*FRE!$M$187,2) -> 0 | O50: =IF($O$24=$T$20,T50,IF($O$24=$X$20,X50,IF($O$24=$AB$20,AB50,AF50))) -> 0.03 | P50: a | Q50: =IF(OR(FRE!$N$189="não",FRE!$N$189<"0"), IF($O$24=$T$20,U50,IF($O$24=$X$20,Y50,IF($O$24=$AB$20,AC50,AG50))), IF($O$24=$T$20,V50,IF($O$24=$X$20,Z50,IF($O$24=$AB$20,AD50,AH50)))) -> 0.06 | R50: =IF(K50>Q50,"Excedeu limites",IF(K50<O50,"Abaixo do limite","ok")) -> ok | T50: 0.03 | U50: 0.06 | V50: 0.07 | X50: 0.025 | Y50: 0.06 | Z50: 0.07 | AB50: 0.01 | AC50: 0.06 | AD50: 0.07 | AF50: 0.025 | AG50: 0.06 | AH50: 0.07 | AI50: =SUM(Orç_analítico_Hab!M174:'Orç_analítico_Hab'!M182)/IF(Orç_analítico_Hab!M$430=0,1,Orç_analítico_Hab!M$430) -> 0 | AJ50: =AI50-ROUND(AI50,4)+AJ49 -> 0 | AK50: =ROUND(L50,2) -> 0
B51: 6.3 | C51: revestimentos externos | K51: 0.04 | L51: =ROUND(K51*FRE!$M$187,2) -> 0 | O51: =IF($O$24=$T$20,T51,IF($O$24=$X$20,X51,IF($O$24=$AB$20,AB51,AF51))) -> 0.04 | P51: a | Q51: =IF(OR(FRE!$N$189="não",FRE!$N$189<"0"), IF($O$24=$T$20,U51,IF($O$24=$X$20,Y51,IF($O$24=$AB$20,AC51,AG51))), IF($O$24=$T$20,V51,IF($O$24=$X$20,Z51,IF($O$24=$AB$20,AD51,AH51)))) -> 0.08 | R51: =IF(K51>Q51,"Excedeu limites",IF(K51<O51,"Abaixo do limite","ok")) -> ok | T51: 0.04 | U51: 0.08 | V51: 0.095 | X51: 0.04 | Y51: 0.06 | Z51: 0.07 | AB51: 0.04 | AC51: 0.08 | AD51: 0.095 | AF51: 0.02 | AG51: 0.06 | AH51: 0.07 | AI51: =SUM(Orç_analítico_Hab!M185:'Orç_analítico_Hab'!M191)/IF(Orç_analítico_Hab!M$430=0,1,Orç_analítico_Hab!M$430) -> 0 | AJ51: =AI51-ROUND(AI51,4)+AJ50 -> 0 | AK51: =ROUND(L51,2) -> 0
B52: 6.4 | C52: forros | K52: 0.005 | L52: =ROUND(K52*FRE!$M$187,2) -> 0 | O52: =IF($O$24=$T$20,T52,IF($O$24=$X$20,X52,IF($O$24=$AB$20,AB52,AF52))) -> 0.005 | P52: a | Q52: =IF(OR(FRE!$N$189="não",FRE!$N$189<"0"), IF($O$24=$T$20,U52,IF($O$24=$X$20,Y52,IF($O$24=$AB$20,AC52,AG52))), IF($O$24=$T$20,V52,IF($O$24=$X$20,Z52,IF($O$24=$AB$20,AD52,AH52)))) -> 0.04 | R52: =IF(K52>Q52,"Excedeu limites",IF(K52<O52,"Abaixo do limite","ok")) -> ok | T52: 0.005 | U52: 0.04 | V52: 0.045 | X52: 0.005 | Y52: 0.03 | Z52: 0.035 | AB52: 0.005 | AC52: 0.03 | AD52: 0.035 | AF52: 0 | AG52: 0.03 | AH52: 0.035 | AI52: =SUM(Orç_analítico_Hab!M194:'Orç_analítico_Hab'!M199)/IF(Orç_analítico_Hab!M$430=0,1,Orç_analítico_Hab!M$430) -> 0 | AJ52: =AI52-ROUND(AI52,4)+AJ51 -> 0 | AK52: =ROUND(L52,2) -> 0
B53: 6.5 | C53: pinturas | K53: 0.06 | L53: =ROUND(K53*FRE!$M$187,2) -> 0 | O53: =IF($O$24=$T$20,T53,IF($O$24=$X$20,X53,IF($O$24=$AB$20,AB53,AF53))) -> 0.06 | P53: a | Q53: =IF(OR(FRE!$N$189="não",FRE!$N$189<"0"), IF($O$24=$T$20,U53,IF($O$24=$X$20,Y53,IF($O$24=$AB$20,AC53,AG53))), IF($O$24=$T$20,V53,IF($O$24=$X$20,Z53,IF($O$24=$AB$20,AD53,AH53)))) -> 0.09 | R53: =IF(K53>Q53,"Excedeu limites",IF(K53<O53,"Abaixo do limite","ok")) -> ok | T53: 0.06 | U53: 0.09 | V53: 0.105 | X53: 0.05 | Y53: 0.09 | Z53: 0.1 | AB53: 0.025 | AC53: 0.09 | AD53: 0.1 | AF53: 0.07 | AG53: 0.12 | AH53: 0.14 | AI53: =SUM(Orç_analítico_Hab!M202:'Orç_analítico_Hab'!M217)/IF(Orç_analítico_Hab!M$430=0,1,Orç_analítico_Hab!M$430) -> 0 | AJ53: =AI53-ROUND(AI53,4)+AJ52 -> 0 | AK53: =ROUND(L53,2) -> 0
B54: 6.6 | C54: especiais / elementos fachadas | K54: 0 | L54: =ROUND(K54*FRE!$M$187,2) -> 0 | O54: =IF($O$24=$T$20,T54,IF($O$24=$X$20,X54,IF($O$24=$AB$20,AB54,AF54))) -> 0 | P54: a | Q54: =IF(OR(FRE!$N$189="não",FRE!$N$189<"0"), IF($O$24=$T$20,U54,IF($O$24=$X$20,Y54,IF($O$24=$AB$20,AC54,AG54))), IF($O$24=$T$20,V54,IF($O$24=$X$20,Z54,IF($O$24=$AB$20,AD54,AH54)))) -> 0.02 | R54: =IF(K54>Q54,"Excedeu limites",IF(K54<O54,"Abaixo do limite","ok")) -> ok | T54: 0 | U54: 0.02 | V54: 0.025 | X54: 0 | Y54: 0.05 | Z54: 0.06 | AB54: 0.01 | AC54: 0.05 | AD54: 0.06 | AF54: 0 | AG54: 0.05 | AH54: 0.06 | AI54: =SUM(Orç_analítico_Hab!M220:'Orç_analítico_Hab'!M227)/IF(Orç_analítico_Hab!M$430=0,1,Orç_analítico_Hab!M$430) -> 0 | AJ54: =AI54-ROUND(AI54,4)+AJ53 -> 0 | AK54: =ROUND(L54,2) -> 0
B55: 7 | C55: PAVIMENTAÇÃO | K55: =SUM(K56:K61) -> 0.06 | L55: =SUM(L56:L61) -> 0 | M55: =IF(SUM($L$25,$L$36,$L$39,$L$40,$L$45,$L$48,$L$55,$L$62,$L$71,$L$75)=0,0,M48+L55/SUM($L$25,$L$36,$L$39,$L$40,$L$45,$L$48,$L$55,$L$62,$L$71,$L$75)) -> 0 | AK55: =SUM(AK56:AK61) -> 0
B56: 7.1 | C56: madeira | K56: 0 | L56: =ROUND(K56*FRE!$M$187,2) -> 0 | O56: =IF($O$24=$T$20,T56,IF($O$24=$X$20,X56,IF($O$24=$AB$20,AB56,AF56))) -> 0 | P56: a | Q56: =IF(OR(FRE!$N$189="não",FRE!$N$189<"0"), IF($O$24=$T$20,U56,IF($O$24=$X$20,Y56,IF($O$24=$AB$20,AC56,AG56))), IF($O$24=$T$20,V56,IF($O$24=$X$20,Z56,IF($O$24=$AB$20,AD56,AH56)))) -> 0.04 | R56: =IF(K56>Q56,"Excedeu limites",IF(K56<O56,"Abaixo do limite","ok")) -> ok | T56: 0 | U56: 0.04 | V56: 0.045 | X56: 0 | Y56: 0.04 | Z56: 0.045 | AB56: 0 | AC56: 0.04 | AD56: 0.045 | AF56: 0 | AG56: 0.04 | AH56: 0.045 | AI56: =SUM(Orç_analítico_Hab!M232:'Orç_analítico_Hab'!M238)/IF(Orç_analítico_Hab!M$430=0,1,Orç_analítico_Hab!M$430) -> 0 | AJ56: =AI56-ROUND(AI56,4)+AJ54 -> 0 | AK56: =ROUND(L56,2) -> 0
B57: 7.2 | C57: cerâmica | K57: 0.035 | L57: =ROUND(K57*FRE!$M$187,2) -> 0 | O57: =IF($O$24=$T$20,T57,IF($O$24=$X$20,X57,IF($O$24=$AB$20,AB57,AF57))) -> 0.01 | P57: a | Q57: =IF(OR(FRE!$N$189="não",FRE!$N$189<"0"), IF($O$24=$T$20,U57,IF($O$24=$X$20,Y57,IF($O$24=$AB$20,AC57,AG57))), IF($O$24=$T$20,V57,IF($O$24=$X$20,Z57,IF($O$24=$AB$20,AD57,AH57)))) -> 0.1 | R57: =IF(K57>Q57,"Excedeu limites",IF(K57<O57,"Abaixo do limite","ok")) -> ok | T57: 0.01 | U57: 0.1 | V57: 0.12 | X57: 0.02 | Y57: 0.07 | Z57: 0.085 | AB57: 0.02 | AC57: 0.07 | AD57: 0.085 | AF57: 0.02 | AG57: 0.07 | AH57: 0.085 | AI57: =SUM(Orç_analítico_Hab!M241:'Orç_analítico_Hab'!M246)/IF(Orç_analítico_Hab!M$430=0,1,Orç_analítico_Hab!M$430) -> 0 | AJ57: =AI57-ROUND(AI57,4)+AJ56 -> 0 | AK57: =ROUND(L57,2) -> 0
B58: 7.3 | C58: carpete | K58: =ROUND(AI58,4) -> 0 | L58: =ROUND(K58*FRE!$M$187,2) -> 0 | O58: =IF($O$24=$T$20,T58,IF($O$24=$X$20,X58,IF($O$24=$AB$20,AB58,AF58))) -> 0 | P58: a | Q58: =IF(OR(FRE!$N$189="não",FRE!$N$189<"0"), IF($O$24=$T$20,U58,IF($O$24=$X$20,Y58,IF($O$24=$AB$20,AC58,AG58))), IF($O$24=$T$20,V58,IF($O$24=$X$20,Z58,IF($O$24=$AB$20,AD58,AH58)))) -> 0.03 | R58: =IF(K58>Q58,"Excedeu limites",IF(K58<O58,"Abaixo do limite","ok")) -> ok | T58: 0 | U58: 0.03 | V58: 0.035 | X58: 0 | Y58: 0.03 | Z58: 0.035 | AB58: 0 | AC58: 0.03 | AD58: 0.035 | AF58: 0 | AG58: 0.03 | AH58: 0.035 | AI58: =SUM(Orç_analítico_Hab!M249:'Orç_analítico_Hab'!M253)/IF(Orç_analítico_Hab!M$430=0,1,Orç_analítico_Hab!M$430) -> 0 | AJ58: =AI58-ROUND(AI58,4)+AJ57 -> 0 | AK58: =ROUND(L58,2) -> 0
B59: 7.4 | C59: cimentados | K59: 0.015 | L59: =ROUND(K59*FRE!$M$187,2) -> 0 | O59: =IF($O$24=$T$20,T59,IF($O$24=$X$20,X59,IF($O$24=$AB$20,AB59,AF59))) -> 0.015 | P59: a | Q59: =IF(OR(FRE!$N$189="não",FRE!$N$189<"0"), IF($O$24=$T$20,U59,IF($O$24=$X$20,Y59,IF($O$24=$AB$20,AC59,AG59))), IF($O$24=$T$20,V59,IF($O$24=$X$20,Z59,IF($O$24=$AB$20,AD59,AH59)))) -> 0.035 | R59: =IF(K59>Q59,"Excedeu limites",IF(K59<O59,"Abaixo do limite","ok")) -> ok | T59: 0.015 | U59: 0.035 | V59: 0.04 | X59: 0.01 | Y59: 0.03 | Z59: 0.035 | AB59: 0.01 | AC59: 0.03 | AD59: 0.035 | AF59: 0.01 | AG59: 0.03 | AH59: 0.035 | AI59: =SUM(Orç_analítico_Hab!M256:'Orç_analítico_Hab'!M260)/IF(Orç_analítico_Hab!M$430=0,1,Orç_analítico_Hab!M$430) -> 0 | AJ59: =AI59-ROUND(AI59,4)+AJ58 -> 0 | AK59: =ROUND(L59,2) -> 0
B60: 7.5 | C60: rodapés, soleiras e peitoris | K60: 0.01 | L60: =ROUND(K60*FRE!$M$187,2) -> 0 | O60: =IF($O$24=$T$20,T60,IF($O$24=$X$20,X60,IF($O$24=$AB$20,AB60,AF60))) -> 0.01 | P60: a | Q60: =IF(OR(FRE!$N$189="não",FRE!$N$189<"0"), IF($O$24=$T$20,U60,IF($O$24=$X$20,Y60,IF($O$24=$AB$20,AC60,AG60))), IF($O$24=$T$20,V60,IF($O$24=$X$20,Z60,IF($O$24=$AB$20,AD60,AH60)))) -> 0.04 | R60: =IF(K60>Q60,"Excedeu limites",IF(K60<O60,"Abaixo do limite","ok")) -> ok | T60: 0.01 | U60: 0.04 | V60: 0.045 | X60: 0.01 | Y60: 0.04 | Z60: 0.045 | AB60: 0.01 | AC60: 0.04 | AD60: 0.045 | AF60: 0.01 | AG60: 0.04 | AH60: 0.045 | AI60: =SUM(Orç_analítico_Hab!M263:'Orç_analítico_Hab'!M280)/IF(Orç_analítico_Hab!M$430=0,1,Orç_analítico_Hab!M$430) -> 0 | AJ60: =AI60-ROUND(AI60,4)+AJ59 -> 0 | AK60: =ROUND(L60,2) -> 0
B61: 7.6 | C61: pavimentações especiais | K61: 0 | L61: =ROUND(K61*FRE!$M$187,2) -> 0 | O61: =IF($O$24=$T$20,T61,IF($O$24=$X$20,X61,IF($O$24=$AB$20,AB61,AF61))) -> 0 | P61: a | Q61: =IF(OR(FRE!$N$189="não",FRE!$N$189<"0"), IF($O$24=$T$20,U61,IF($O$24=$X$20,Y61,IF($O$24=$AB$20,AC61,AG61))), IF($O$24=$T$20,V61,IF($O$24=$X$20,Z61,IF($O$24=$AB$20,AD61,AH61)))) -> 0.07 | R61: =IF(K61>Q61,"Excedeu limites",IF(K61<O61,"Abaixo do limite","ok")) -> ok | T61: 0 | U61: 0.07 | V61: 0.08 | X61: 0 | Y61: 0.07 | Z61: 0.085 | AB61: 0 | AC61: 0.07 | AD61: 0.085 | AF61: 0 | AG61: 0.07 | AH61: 0.085 | AI61: =SUM(Orç_analítico_Hab!M283:'Orç_analítico_Hab'!M289)/IF(Orç_analítico_Hab!M$430=0,1,Orç_analítico_Hab!M$430) -> 0 | AJ61: =AI61-ROUND(AI61,4)+AJ60 -> 0 | AK61: =ROUND(L61,2) -> 0
B62: 8 | C62: INSTALAÇÕES | K62: =SUM(K63:K70) -> 0.15 | L62: =SUM(L63:L70) -> 0 | M62: =IF(SUM($L$25,$L$36,$L$39,$L$40,$L$45,$L$48,$L$55,$L$62,$L$71,$L$75)=0,0,M55+L62/SUM($L$25,$L$36,$L$39,$L$40,$L$45,$L$48,$L$55,$L$62,$L$71,$L$75)) -> 0 | AK62: =SUM(AK63:AK70) -> 0
B63: 8.1 | C63: elétricas / telefônicas | K63: 0.05 | L63: =ROUND(K63*FRE!$M$187,2) -> 0 | O63: =IF($O$24=$T$20,T63,IF($O$24=$X$20,X63,IF($O$24=$AB$20,AB63,AF63))) -> 0.05 | P63: a | Q63: =IF(OR(FRE!$N$189="não",FRE!$N$189<"0"), IF($O$24=$T$20,U63,IF($O$24=$X$20,Y63,IF($O$24=$AB$20,AC63,AG63))), IF($O$24=$T$20,V63,IF($O$24=$X$20,Z63,IF($O$24=$AB$20,AD63,AH63)))) -> 0.1 | R63: =IF(K63>Q63,"Excedeu limites",IF(K63<O63,"Abaixo do limite","ok")) -> ok | T63: 0.05 | U63: 0.1 | V63: 0.12 | X63: 0.05 | Y63: 0.1 | Z63: 0.12 | AB63: 0.05 | AC63: 0.1 | AD63: 0.12 | AF63: 0.06 | AG63: 0.1 | AH63: 0.12 | AI63: =SUM(Orç_analítico_Hab!M294:'Orç_analítico_Hab'!M310)/IF(Orç_analítico_Hab!M$430=0,1,Orç_analítico_Hab!M$430) -> 0 | AJ63: =AI63-ROUND(AI63,4)+AJ61 -> 0 | AK63: =ROUND(L63,2) -> 0
B64: 8.2 | C64: hidráulicas / gás / incêndio | K64: 0.05 | L64: =ROUND(K64*FRE!$M$187,2) -> 0 | O64: =IF($O$24=$T$20,T64,IF($O$24=$X$20,X64,IF($O$24=$AB$20,AB64,AF64))) -> 0.05 | P64: a | Q64: =IF(OR(FRE!$N$189="não",FRE!$N$189<"0"), IF($O$24=$T$20,U64,IF($O$24=$X$20,Y64,IF($O$24=$AB$20,AC64,AG64))), IF($O$24=$T$20,V64,IF($O$24=$X$20,Z64,IF($O$24=$AB$20,AD64,AH64)))) -> 0.1 | R64: =IF(K64>Q64,"Excedeu limites",IF(K64<O64,"Abaixo do limite","ok")) -> ok | T64: 0.05 | U64: 0.1 | V64: 0.12 | X64: 0.05 | Y64: 0.1 | Z64: 0.12 | AB64: 0.03 | AC64: 0.08 | AD64: 0.095 | AF64: 0.05 | AG64: 0.1 | AH64: 0.12 | AI64: =SUM(Orç_analítico_Hab!M313:'Orç_analítico_Hab'!M345)/IF(Orç_analítico_Hab!M$430=0,1,Orç_analítico_Hab!M$430) -> 0 | AJ64: =AI64-ROUND(AI64,4)+AJ63 -> 0 | AK64: =ROUND(L64,2) -> 0
B65: 8.3 | C65: sanitárias / pluvial | K65: 0.03 | L65: =ROUND(K65*FRE!$M$187,2) -> 0 | O65: =IF($O$24=$T$20,T65,IF($O$24=$X$20,X65,IF($O$24=$AB$20,AB65,AF65))) -> 0.03 | P65: a | Q65: =IF(OR(FRE!$N$189="não",FRE!$N$189<"0"), IF($O$24=$T$20,U65,IF($O$24=$X$20,Y65,IF($O$24=$AB$20,AC65,AG65))), IF($O$24=$T$20,V65,IF($O$24=$X$20,Z65,IF($O$24=$AB$20,AD65,AH65)))) -> 0.06 | R65: =IF(K65>Q65,"Excedeu limites",IF(K65<O65,"Abaixo do limite","ok")) -> ok | T65: 0.03 | U65: 0.06 | V65: 0.07 | X65: 0.03 | Y65: 0.06 | Z65: 0.07 | AB65: 0.02 | AC65: 0.06 | AD65: 0.07 | AF65: 0.03 | AG65: 0.06 | AH65: 0.07 | AI65: =SUM(Orç_analítico_Hab!M348:'Orç_analítico_Hab'!M355)/IF(Orç_analítico_Hab!M$430=0,1,Orç_analítico_Hab!M$430) -> 0 | AJ65: =AI65-ROUND(AI65,4)+AJ64 -> 0 | AK65: =ROUND(L65,2) -> 0
B66: 8.4 | C66: aparelhos, metais e bancadas | K66: 0.02 | L66: =ROUND(K66*FRE!$M$187,2) -> 0 | O66: =IF($O$24=$T$20,T66,IF($O$24=$X$20,X66,IF($O$24=$AB$20,AB66,AF66))) -> 0.02 | P66: a | Q66: =IF(OR(FRE!$N$189="não",FRE!$N$189<"0"), IF($O$24=$T$20,U66,IF($O$24=$X$20,Y66,IF($O$24=$AB$20,AC66,AG66))), IF($O$24=$T$20,V66,IF($O$24=$X$20,Z66,IF($O$24=$AB$20,AD66,AH66)))) -> 0.05 | R66: =IF(K66>Q66,"Excedeu limites",IF(K66<O66,"Abaixo do limite","ok")) -> ok | T66: 0.02 | U66: 0.05 | V66: 0.06 | X66: 0.02 | Y66: 0.05 | Z66: 0.06 | AB66: 0.02 | AC66: 0.05 | AD66: 0.06 | AF66: 0.02 | AG66: 0.05 | AH66: 0.06 | AI66: =SUM(Orç_analítico_Hab!M365:'Orç_analítico_Hab'!M377)/IF(Orç_analítico_Hab!M$430=0,1,Orç_analítico_Hab!M$430) -> 0 | AJ66: =AI66-ROUND(AI66,4)+AJ65 -> 0 | AK66: =ROUND(L66,2) -> 0
B67: 8.5 | C67: elevadores / bombas | K67: =ROUND(AI67,4) -> 0 | L67: =ROUND(K67*FRE!$M$187,2) -> 0 | O67: =IF($O$24=$T$20,T67,IF($O$24=$X$20,X67,IF($O$24=$AB$20,AB67,AF67))) -> 0 | P67: a | Q67: =IF(OR(FRE!$N$189="não",FRE!$N$189<"0"), IF($O$24=$T$20,U67,IF($O$24=$X$20,Y67,IF($O$24=$AB$20,AC67,AG67))), IF($O$24=$T$20,V67,IF($O$24=$X$20,Z67,IF($O$24=$AB$20,AD67,AH67)))) -> 0.01 | R67: =IF(K67>Q67,"Excedeu limites",IF(K67<O67,"Abaixo do limite","ok")) -> ok | T67: 0 | U67: 0.01 | V67: 0.015 | X67: 0 | Y67: 0.05 | Z67: 0.06 | AB67: 0.03 | AC67: 0.06 | AD67: 0.07 | AF67: 0 | AG67: 0.05 | AH67: 0.06 | AI67: =SUM(Orç_analítico_Hab!M358:'Orç_analítico_Hab'!M362)/IF(Orç_analítico_Hab!M$430=0,1,Orç_analítico_Hab!M$430) -> 0 | AJ67: =AI67-ROUND(AI67,4)+AJ66 -> 0 | AK67: =ROUND(L67,2) -> 0
B68: 8.6 | C68: climatização | K68: =ROUND(AI68,4) -> 0 | L68: =ROUND(K68*FRE!$M$187,2) -> 0 | O68: =IF($O$24=$T$20,T68,IF($O$24=$X$20,X68,IF($O$24=$AB$20,AB68,AF68))) -> 0 | P68: a | Q68: =IF(OR(FRE!$N$189="não",FRE!$N$189<"0"), IF($O$24=$T$20,U68,IF($O$24=$X$20,Y68,IF($O$24=$AB$20,AC68,AG68))), IF($O$24=$T$20,V68,IF($O$24=$X$20,Z68,IF($O$24=$AB$20,AD68,AH68)))) -> 0.03 | R68: =IF(K68>Q68,"Excedeu limites",IF(K68<O68,"Abaixo do limite","ok")) -> ok | T68: 0 | U68: 0.03 | V68: 0.035 | X68: 0 | Y68: 0.04 | Z68: 0.045 | AB68: 0.005 | AC68: 0.05 | AD68: 0.06 | AF68: 0 | AG68: 0.04 | AH68: 0.045 | AI68: =SUM(Orç_analítico_Hab!M380:'Orç_analítico_Hab'!M386)/IF(Orç_analítico_Hab!M$430=0,1,Orç_analítico_Hab!M$430) -> 0 | AJ68: =AI68-ROUND(AI68,4)+AJ67 -> 0 | AK68: =ROUND(L68,2) -> 0
B69: 8.7 | C69: lógica | K69: =ROUND(AI69,4) -> 0 | L69: =ROUND(K69*FRE!$M$187,2) -> 0 | O69: =IF($O$24=$T$20,T69,IF($O$24=$X$20,X69,IF($O$24=$AB$20,AB69,AF69))) -> 0 | P69: a | Q69: =IF(OR(FRE!$N$189="não",FRE!$N$189<"0"), IF($O$24=$T$20,U69,IF($O$24=$X$20,Y69,IF($O$24=$AB$20,AC69,AG69))), IF($O$24=$T$20,V69,IF($O$24=$X$20,Z69,IF($O$24=$AB$20,AD69,AH69)))) -> 0.01 | R69: =IF(K69>Q69,"Excedeu limites",IF(K69<O69,"Abaixo do limite","ok")) -> ok | T69: 0 | U69: 0.01 | V69: 0.01 | X69: 0 | Y69: 0.01 | Z69: 0.01 | AB69: 0 | AC69: 0.01 | AD69: 0.01 | AF69: 0 | AG69: 0.01 | AH69: 0.01 | AI69: =SUM(Orç_analítico_Hab!M389:'Orç_analítico_Hab'!M396)/IF(Orç_analítico_Hab!M$430=0,1,Orç_analítico_Hab!M$430) -> 0 | AJ69: =AI69-ROUND(AI69,4)+AJ68 -> 0 | AK69: =ROUND(L69,2) -> 0
B70: 8.8 | C70: especiais | K70: =ROUND(AI70,4) -> 0 | L70: =ROUND(K70*FRE!$M$187,2) -> 0 | O70: =IF($O$24=$T$20,T70,IF($O$24=$X$20,X70,IF($O$24=$AB$20,AB70,AF70))) -> 0 | P70: a | Q70: =IF(OR(FRE!$N$189="não",FRE!$N$189<"0"), IF($O$24=$T$20,U70,IF($O$24=$X$20,Y70,IF($O$24=$AB$20,AC70,AG70))), IF($O$24=$T$20,V70,IF($O$24=$X$20,Z70,IF($O$24=$AB$20,AD70,AH70)))) -> 0.01 | R70: =IF(K70>Q70,"Excedeu limites",IF(K70<O70,"Abaixo do limite","ok")) -> ok | T70: 0 | U70: 0.01 | V70: 0.01 | X70: 0 | Y70: 0.01 | Z70: 0.01 | AB70: 0 | AC70: 0.01 | AD70: 0.01 | AF70: 0 | AG70: 0.01 | AH70: 0.01 | AI70: =SUM(Orç_analítico_Hab!M399:'Orç_analítico_Hab'!M406)/IF(Orç_analítico_Hab!M$430=0,1,Orç_analítico_Hab!M$430) -> 0 | AJ70: =AI70-ROUND(AI70,4)+AJ69 -> 0 | AK70: =ROUND(L70,2) -> 0
B71: 9 | C71: COMPLEMENTAÇÕES | K71: =SUM(K72:K74) -> 0.015 | L71: =SUM(L72:L74) -> 0 | M71: =IF(SUM($L$25,$L$36,$L$39,$L$40,$L$45,$L$48,$L$55,$L$62,$L$71,$L$75)=0,0,M62+L71/SUM($L$25,$L$36,$L$39,$L$40,$L$45,$L$48,$L$55,$L$62,$L$71,$L$75)) -> 0 | AK71: =SUM(AK72:AK74) -> 0
B72: 9.1 | C72: calafete / limpeza | K72: 0.005 | L72: =ROUND(K72*FRE!$M$187,2) -> 0 | O72: =IF($O$24=$T$20,T72,IF($O$24=$X$20,X72,IF($O$24=$AB$20,AB72,AF72))) -> 0.005 | P72: a | Q72: =IF(OR(FRE!$N$189="não",FRE!$N$189<"0"), IF($O$24=$T$20,U72,IF($O$24=$X$20,Y72,IF($O$24=$AB$20,AC72,AG72))), IF($O$24=$T$20,V72,IF($O$24=$X$20,Z72,IF($O$24=$AB$20,AD72,AH72)))) -> 0.02 | R72: =IF(K72>Q72,"Excedeu limites",IF(K72<O72,"Abaixo do limite","ok")) -> ok | T72: 0.005 | U72: 0.02 | V72: 0.025 | X72: 0.005 | Y72: 0.02 | Z72: 0.025 | AB72: 0.01 | AC72: 0.02 | AD72: 0.025 | AF72: 0.005 | AG72: 0.02 | AH72: 0.025 | AI72: =Orç_analítico_Hab!M410/IF(Orç_analítico_Hab!M$430=0,1,Orç_analítico_Hab!M$430) -> 0 | AJ72: =AI72-ROUND(AI72,4)+AJ70 -> 0 | AK72: =ROUND(K72*(FRE!$O$187),2) -> 0
B73: 9.2 | C73: ligações definitivas | K73: 0.01 | L73: =ROUND(K73*FRE!$M$187,2) -> 0 | O73: =IF($O$24=$T$20,T73,IF($O$24=$X$20,X73,IF($O$24=$AB$20,AB73,AF73))) -> 0.01 | P73: a | Q73: =IF(OR(FRE!$N$189="não",FRE!$N$189<"0"), IF($O$24=$T$20,U73,IF($O$24=$X$20,Y73,IF($O$24=$AB$20,AC73,AG73))), IF($O$24=$T$20,V73,IF($O$24=$X$20,Z73,IF($O$24=$AB$20,AD73,AH73)))) -> 0.03 | R73: =IF(K73>Q73,"Excedeu limites",IF(K73<O73,"Abaixo do limite","ok")) -> ok | T73: 0.01 | U73: 0.03 | V73: 0.035 | X73: 0.02 | Y73: 0.03 | Z73: 0.035 | AB73: 0.015 | AC73: 0.03 | AD73: 0.035 | AF73: 0.02 | AG73: 0.03 | AH73: 0.035 | AI73: =Orç_analítico_Hab!M411/IF(Orç_analítico_Hab!M$430=0,1,Orç_analítico_Hab!M$430) -> 0 | AJ73: =AI73-ROUND(AI73,4)+AJ72 -> 0 | AK73: =ROUND(L73,2) -> 0
B74: 9.3 | C74: outros | K74: =ROUND(AI74,4) -> 0 | L74: =ROUND(K74*FRE!$M$187,2) -> 0 | O74: =IF($O$24=$T$20,T74,IF($O$24=$X$20,X74,IF($O$24=$AB$20,AB74,AF74))) -> 0 | P74: a | Q74: =IF(OR(FRE!$N$189="não",FRE!$N$189<"0"), IF($O$24=$T$20,U74,IF($O$24=$X$20,Y74,IF($O$24=$AB$20,AC74,AG74))), IF($O$24=$T$20,V74,IF($O$24=$X$20,Z74,IF($O$24=$AB$20,AD74,AH74)))) -> 0.01 | R74: =IF(K74>Q74,"Excedeu limites",IF(K74<O74,"Abaixo do limite","ok")) -> ok | T74: 0 | U74: 0.01 | V74: 0.01 | X74: 0 | Y74: 0.01 | Z74: 0.01 | AB74: 0 | AC74: 0.01 | AD74: 0.01 | AF74: 0 | AG74: 0.01 | AH74: 0.01 | AI74: =SUM(Orç_analítico_Hab!M412:'Orç_analítico_Hab'!M414)/IF(Orç_analítico_Hab!M$430=0,1,Orç_analítico_Hab!M$430) -> 0 | AJ74: =AI74-ROUND(AI74,4)+AJ73 -> 0 | AK74: =ROUND(L74,2) -> 0
B75: 10 | C75: INFRAESTRUTURA E URBANIZAÇÃO | K75: =SUM(K76:K85) -> 0.15 | L75: =SUM(L76:L85) -> 0 | M75: =IF(SUM($L$25,$L$36,$L$39,$L$40,$L$45,$L$48,$L$55,$L$62,$L$71,$L$75)=0,0,M71+L75/SUM($L$25,$L$36,$L$39,$L$40,$L$45,$L$48,$L$55,$L$62,$L$71,$L$75)) -> 0 | AK75: =SUM(AK76:AK85) -> 0
B76: 10.1 | C76: terraplenagem | K76: 0.03 | L76: =ROUND(K76*FRE!$M$187,2) -> 0 | O76: =IF($O$24=$T$20,T76,IF($O$24=$X$20,X76,IF($O$24=$AB$20,AB76,AF76))) -> 0 | P76: a | Q76: =IF(OR(FRE!$N$189="não",FRE!$N$189<"0"), IF($O$24=$T$20,U76,IF($O$24=$X$20,Y76,IF($O$24=$AB$20,AC76,AG76))), IF($O$24=$T$20,V76,IF($O$24=$X$20,Z76,IF($O$24=$AB$20,AD76,AH76)))) -> 0.03 | R76: =IF(K76>Q76,"Excedeu limites",IF(K76<O76,"Abaixo do limite","ok")) -> ok | T76: 0 | U76: 0.03 | X76: 0 | Y76: 0.03 | AB76: 0 | AC76: 0.03 | AF76: 0 | AG76: 0.03 | AI76: =Orç_analítico_Hab!M418/IF(Orç_analítico_Hab!M$430=0,1,Orç_analítico_Hab!M$430) -> 0 | AJ76: =AI76-ROUND(AI76,4)+AJ74 -> 0 | AK76: =ROUND(L76,2) -> 0
B77: 10.2 | C77: água potável | K77: 0.015 | L77: =ROUND(K77*FRE!$M$187,2) -> 0 | O77: =IF($O$24=$T$20,T77,IF($O$24=$X$20,X77,IF($O$24=$AB$20,AB77,AF77))) -> 0 | P77: a | Q77: =IF(OR(FRE!$N$189="não",FRE!$N$189<"0"), IF($O$24=$T$20,U77,IF($O$24=$X$20,Y77,IF($O$24=$AB$20,AC77,AG77))), IF($O$24=$T$20,V77,IF($O$24=$X$20,Z77,IF($O$24=$AB$20,AD77,AH77)))) -> 0.015 | R77: =IF(K77>Q77,"Excedeu limites",IF(K77<O77,"Abaixo do limite","ok")) -> ok | T77: 0 | U77: 0.015 | X77: 0 | Y77: 0.015 | AB77: 0 | AC77: 0.015 | AF77: 0 | AG77: 0.015 | AI77: =Orç_analítico_Hab!M419/IF(Orç_analítico_Hab!M$430=0,1,Orç_analítico_Hab!M$430) -> 0 | AJ77: =AI77-ROUND(AI77,4)+AJ76 -> 0 | AK77: =ROUND(L77,2) -> 0
B78: 10.3 | C78: esgoto sanitário | K78: 0.02 | L78: =ROUND(K78*FRE!$M$187,2) -> 0 | O78: =IF($O$24=$T$20,T78,IF($O$24=$X$20,X78,IF($O$24=$AB$20,AB78,AF78))) -> 0 | P78: a | Q78: =IF(OR(FRE!$N$189="não",FRE!$N$189<"0"), IF($O$24=$T$20,U78,IF($O$24=$X$20,Y78,IF($O$24=$AB$20,AC78,AG78))), IF($O$24=$T$20,V78,IF($O$24=$X$20,Z78,IF($O$24=$AB$20,AD78,AH78)))) -> 0.02 | R78: =IF(K78>Q78,"Excedeu limites",IF(K78<O78,"Abaixo do limite","ok")) -> ok | T78: 0 | U78: 0.02 | X78: 0 | Y78: 0.02 | AB78: 0 | AC78: 0.02 | AF78: 0 | AG78: 0.02 | AI78: =Orç_analítico_Hab!M420/IF(Orç_analítico_Hab!M$430=0,1,Orç_analítico_Hab!M$430) -> 0 | AJ78: =AI78-ROUND(AI78,4)+AJ77 -> 0 | AK78: =ROUND(L78,2) -> 0
B79: 10.4 | C79: drenagem das águas pluviais | K79: 0.015 | L79: =ROUND(K79*FRE!$M$187,2) -> 0 | O79: =IF($O$24=$T$20,T79,IF($O$24=$X$20,X79,IF($O$24=$AB$20,AB79,AF79))) -> 0 | P79: a | Q79: =IF(OR(FRE!$N$189="não",FRE!$N$189<"0"), IF($O$24=$T$20,U79,IF($O$24=$X$20,Y79,IF($O$24=$AB$20,AC79,AG79))), IF($O$24=$T$20,V79,IF($O$24=$X$20,Z79,IF($O$24=$AB$20,AD79,AH79)))) -> 0.015 | R79: =IF(K79>Q79,"Excedeu limites",IF(K79<O79,"Abaixo do limite","ok")) -> ok | T79: 0 | U79: 0.015 | X79: 0 | Y79: 0.015 | AB79: 0 | AC79: 0.015 | AF79: 0 | AG79: 0.015 | AI79: =Orç_analítico_Hab!M421/IF(Orç_analítico_Hab!M$430=0,1,Orç_analítico_Hab!M$430) -> 0 | AJ79: =AI79-ROUND(AI79,4)+AJ78 -> 0 | AK79: =ROUND(L79,2) -> 0
B80: 10.5 | C80: pavimentação | K80: 0.015 | L80: =ROUND(K80*FRE!$M$187,2) -> 0 | O80: =IF($O$24=$T$20,T80,IF($O$24=$X$20,X80,IF($O$24=$AB$20,AB80,AF80))) -> 0.01 | P80: a | Q80: =IF(OR(FRE!$N$189="não",FRE!$N$189<"0"), IF($O$24=$T$20,U80,IF($O$24=$X$20,Y80,IF($O$24=$AB$20,AC80,AG80))), IF($O$24=$T$20,V80,IF($O$24=$X$20,Z80,IF($O$24=$AB$20,AD80,AH80)))) -> 0.015 | R80: =IF(K80>Q80,"Excedeu limites",IF(K80<O80,"Abaixo do limite","ok")) -> ok | T80: 0.01 | U80: 0.015 | X80: 0.01 | Y80: 0.015 | AB80: 0.01 | AC80: 0.015 | AF80: 0.01 | AG80: 0.015 | AI80: =Orç_analítico_Hab!M422/IF(Orç_analítico_Hab!M$430=0,1,Orç_analítico_Hab!M$430) -> 0 | AJ80: =AI80-ROUND(AI80,4)+AJ79 -> 0 | AK80: =ROUND(L80,2) -> 0
B81: 10.6 | C81: energia e iluminação | K81: 0.015 | L81: =ROUND(K81*FRE!$M$187,2) -> 0 | O81: =IF($O$24=$T$20,T81,IF($O$24=$X$20,X81,IF($O$24=$AB$20,AB81,AF81))) -> 0.002 | P81: a | Q81: =IF(OR(FRE!$N$189="não",FRE!$N$189<"0"), IF($O$24=$T$20,U81,IF($O$24=$X$20,Y81,IF($O$24=$AB$20,AC81,AG81))), IF($O$24=$T$20,V81,IF($O$24=$X$20,Z81,IF($O$24=$AB$20,AD81,AH81)))) -> 0.015 | R81: =IF(K81>Q81,"Excedeu limites",IF(K81<O81,"Abaixo do limite","ok")) -> ok | T81: 0.002 | U81: 0.015 | X81: 0.002 | Y81: 0.015 | AB81: 0.002 | AC81: 0.015 | AF81: 0.002 | AG81: 0.015 | AI81: =Orç_analítico_Hab!M423/IF(Orç_analítico_Hab!M$430=0,1,Orç_analítico_Hab!M$430) -> 0 | AJ81: =AI81-ROUND(AI81,4)+AJ80 -> 0 | AK81: =ROUND(L81,2) -> 0
B82: 10.7 | C82: telefone | K82: 0.01 | L82: =ROUND(K82*FRE!$M$187,2) -> 0 | O82: =IF($O$24=$T$20,T82,IF($O$24=$X$20,X82,IF($O$24=$AB$20,AB82,AF82))) -> 0 | P82: a | Q82: =IF(OR(FRE!$N$189="não",FRE!$N$189<"0"), IF($O$24=$T$20,U82,IF($O$24=$X$20,Y82,IF($O$24=$AB$20,AC82,AG82))), IF($O$24=$T$20,V82,IF($O$24=$X$20,Z82,IF($O$24=$AB$20,AD82,AH82)))) -> 0.01 | R82: =IF(K82>Q82,"Excedeu limites",IF(K82<O82,"Abaixo do limite","ok")) -> ok | T82: 0 | U82: 0.01 | X82: 0 | Y82: 0.01 | AB82: 0 | AC82: 0.01 | AF82: 0 | AG82: 0.01 | AI82: =Orç_analítico_Hab!M424/IF(Orç_analítico_Hab!M$430=0,1,Orç_analítico_Hab!M$430) -> 0 | AJ82: =AI82-ROUND(AI82,4)+AJ81 -> 0 | AK82: =ROUND(L82,2) -> 0
B83: 10.8 | C83: gás | K83: 0.002 | L83: =ROUND(K83*FRE!$M$187,2) -> 0 | O83: =IF($O$24=$T$20,T83,IF($O$24=$X$20,X83,IF($O$24=$AB$20,AB83,AF83))) -> 0 | P83: a | Q83: =IF(OR(FRE!$N$189="não",FRE!$N$189<"0"), IF($O$24=$T$20,U83,IF($O$24=$X$20,Y83,IF($O$24=$AB$20,AC83,AG83))), IF($O$24=$T$20,V83,IF($O$24=$X$20,Z83,IF($O$24=$AB$20,AD83,AH83)))) -> 0.01 | R83: =IF(K83>Q83,"Excedeu limites",IF(K83<O83,"Abaixo do limite","ok")) -> ok | T83: 0 | U83: 0.01 | X83: 0 | Y83: 0.01 | AB83: 0 | AC83: 0.01 | AF83: 0 | AG83: 0.01 | AI83: =Orç_analítico_Hab!M425/IF(Orç_analítico_Hab!M$430=0,1,Orç_analítico_Hab!M$430) -> 0 | AJ83: =AI83-ROUND(AI83,4)+AJ82 -> 0 | AK83: =ROUND(L83,2) -> 0
B84: 10.9 | C84: obras especiais | K84: 0.018 | L84: =ROUND(K84*FRE!$M$187,2) -> 0 | O84: =IF($O$24=$T$20,T84,IF($O$24=$X$20,X84,IF($O$24=$AB$20,AB84,AF84))) -> 0 | P84: a | Q84: =IF(OR(FRE!$N$189="não",FRE!$N$189<"0"), IF($O$24=$T$20,U84,IF($O$24=$X$20,Y84,IF($O$24=$AB$20,AC84,AG84))), IF($O$24=$T$20,V84,IF($O$24=$X$20,Z84,IF($O$24=$AB$20,AD84,AH84)))) -> 0.02 | R84: =IF(K84>Q84,"Excedeu limites",IF(K84<O84,"Abaixo do limite","ok")) -> ok | T84: 0 | U84: 0.02 | X84: 0 | Y84: 0.02 | AB84: 0 | AC84: 0.02 | AF84: 0 | AG84: 0.02 | AI84: =Orç_analítico_Hab!M426/IF(Orç_analítico_Hab!M$430=0,1,Orç_analítico_Hab!M$430) -> 0 | AJ84: =AI84-ROUND(AI84,4)+AJ83 -> 0 | AK84: =ROUND(L84,2) -> 0
B85: 10.10 | C85: paisagismo, equipamentos e ambientação | K85: 0.01 | L85: =ROUND(K85*FRE!$M$187,2) -> 0 | O85: =IF($O$24=$T$20,T85,IF($O$24=$X$20,X85,IF($O$24=$AB$20,AB85,AF85))) -> 0 | P85: a | Q85: =IF(OR(FRE!$N$189="não",FRE!$N$189<"0"), IF($O$24=$T$20,U85,IF($O$24=$X$20,Y85,IF($O$24=$AB$20,AC85,AG85))), IF($O$24=$T$20,V85,IF($O$24=$X$20,Z85,IF($O$24=$AB$20,AD85,AH85)))) -> 0.01 | R85: =IF(K85>Q85,"Excedeu limites",IF(K85<O85,"Abaixo do limite","ok")) -> ok | T85: 0 | U85: 0.01 | X85: 0.01 | Y85: 0.03 | AB85: 0.01 | AC85: 0.03 | AF85: 0.01 | AG85: 0.03 | AI85: =Orç_analítico_Hab!M427/IF(Orç_analítico_Hab!M$430=0,1,Orç_analítico_Hab!M$430) -> 0 | AJ85: =AI85-ROUND(AI85,4)+AJ84 -> 0 | AK85: =ROUND(L85,2) -> 0
C86: =IF(AND(I22="SIM",K75>0),"APAGAR VALORES RELATIVOS A INFRAESTRUTURA NO ORÇAMENTO SINTÉTICO OU ANALITICO DE HABITAÇÃO","TOTAL") -> TOTAL | K86: =IF(SUM(K25,K36,K39:K40,K45,K48,K55,K62,K71,K75)>100%,"Passou "&TEXT((SUM(K25,K36,K39:K40,K45,K48,K55,K62,K71,K75)-100%)*100,"0,00")&"%", IF(SUM(K25,K36,K39:K40,K45,K48,K55,K62,K71,K75)<100%,"Falta "&TEXT((100%-SUM(K25,K36,K39:K40,K45,K48,K55,K62,K71,K75))*100,"0,00")&"%", 100%)) -> 1 | L86: =IF($I$22="não",SUM(L25,L36,L39:L40,L45,L48,L55,L62,L71,L75),SUM(L25,L36,L39:L40,L45,L48,L55,L62,L71)) -> 0 | AK86: =IF($I$22="não",SUM(AK25,AK36,AK39:AK40,AK45,AK48,AK55,AK62,AK71,AK75),SUM(AK25,AK36,AK39:AK40,AK45,AK48,AK55,AK62,AK71)) -> 0
T87: itens finais míminos | X87: itens finais míminos | AB87: itens finais míminos | AF87: itens finais míminos | AK87: =FRE!$O$187-AK86 -> 0
I88: Assinatura do responsável técnico | T88: 50% 1.4 ao 1.10 | X88: 50% 1.4 ao 1.10 | AB88: 50% 1.4 ao 1.10 | AF88: 50% 1.4 ao 1.10
I89: Nome: | J89: =IF(FRE!$B$22="","",FRE!$B$22) -> {RESPONSÁVEL TÉCNICO} | T89: 70% 8.1 ao 8.3 | X89: 70% 8.1 ao 8.3 | AB89: 70% 8.1 ao 8.3 | AF89: 70% 8.1 ao 8.3
I90: CPF: | J90: =IF(FRE!$M$22="","",FRE!$M$22) -> {DOC. RESPONSÁVEL} | T90: 100% 4.2 em diante | X90: 100% 4.2 em diante | AB90: 100% 4.2 em diante | AF90: 100% 4.2 em diante
I91: CREA/CAU: | J91: =IF(FRE!$J$22="","",FRE!$J$22) -> {CREA} | T91: =SUM(T42:T61,T66:T85)+70%*SUM(T63:T65)+50%*SUM(U29:U35) -> 0.4295 | X91: =SUM(X42:X61,X66:X85)+70%*SUM(X63:X65)+50%*SUM(Y29:Y35) -> 0.4365 | AB91: =SUM(AB42:AB61,AB66:AB85)+70%*SUM(AB63:AB65)+50%*SUM(AC29:AC35) -> 0.4155 | AF91: =SUM(AF42:AF61,AF66:AF85)+70%*SUM(AF63:AF65)+50%*SUM(AG29:AG35) -> 0.4185

Sheet Orç_analítico_Hab
A1: (escolha) | L1: Grau de sigilo
A2: Habitacional horizontal | E2: Orçamento Analítico Habitação | L2: #EXTERNO.CONFIDENCIAL
A3: Vertical: habit. / salas / misto
A4: Vertical andar livre | E4: =FRE!$D$4 -> Programa: | F4: =FRE!$E$4 -> Apoio à Produção de Imóveis - Pessoa Jurídica
A5: Vertical parede de concreto
I17: =FRE!N189 -> não | J17: Unidade | K17: Quantidade | L17: Custo unitário | M17: Custo total | N17: % do item
B18: 1 | C18: SERVIÇOS PRELIMINARES E GERAIS
B19: 1.1 | C19: serviços técnicos (projetos, orçamentos, levant. topog., sondagem, licenças e PCMAT) | M19: =ROUND(L19*K19,2) -> 0
B20: 1.2 | C20: instalações e canteiros (barracão, cercamento e placa da obra) | M20: =ROUND(L20*K20,2) -> 0
B21: 1.3 | C21: ligações provisórias (água, energia, telefone e esgoto) | M21: =ROUND(L21*K21,2) -> 0
B22: 1.4 | C22: manutenção canteiro/consumo | M22: =ROUND(L22*K22,2) -> 0
B23: 1.5 | C23: transportes máquinas e equipamentos | M23: =ROUND(L23*K23,2) -> 0
B24: 1.6 | C24: controle tecnológico | M24: =ROUND(L24*K24,2) -> 0
B25: 1.7 | C25: gestão de resíduos | M25: =ROUND(L25*K25,2) -> 0
B26: 1.8 | C26: gestão da qualidade | M26: =ROUND(L26*K26,2) -> 0
B27: 1.9 | C27: equipamentos de proteção coletivos | M27: =ROUND(L27*K27,2) -> 0
B28: 1.10 | C28: administração local (engenheiros, mestres, etc.) | M28: =ROUND(L28*K28,2) -> 0
C29: CUSTO TOTAL DO ITEM | M29: =SUM(M18:M28) -> 0 | N29: =IF($M$430=0,0,M29/$M$430) -> 0
B31: 2 | C31: FUNDAÇÃO E CONTENÇÕES
B32: 2.1 | C32: Trabalhos com terra
B33: 2.1.1 | C33: Demolições | M33: =ROUND(L33*K33,2) -> 0
B34: 2.1.2 | C34: Limpeza do terreno | M34: =ROUND(L34*K34,2) -> 0
B35: 2.1.3 | C35: Escavações mecânicas | M35: =ROUND(L35*K35,2) -> 0
B36: 2.1.4 | C36: Escavaçoes manuais | M36: =ROUND(L36*K36,2) -> 0
B37: 2.1.5 | C37: Aterro e apiloamento | M37: =ROUND(L37*K37,2) -> 0
B38: 2.1.6 | C38: Locação da Obra | D38: Trabalhos em | M38: =ROUND(L38*K38,2) -> 0
B39: 2.1.7 | C39: Desmonte em Rocha | M39: =ROUND(L39*K39,2) -> 0
B40: 2.1.8 | M40: =ROUND(L40*K40,2) -> 0
B41: 2.1.9 | M41: =ROUND(L41*K41,2) -> 0
B42: 2.1.10 | M42: =ROUND(L42*K42,2) -> 0
B44: 2.2 | C44: Fundações e outros serviços
B45: 2.2.1 | C45: Escoramento do Terreno vizinho | M45: =ROUND(L45*K45,2) -> 0
B46: 2.2.2 | C46: Reb. Lençol Freático/Drenagem | M46: =ROUND(L46*K46,2) -> 0
B47: 2.2.3 | C47: Fundações Profundas | M47: =ROUND(L47*K47,2) -> 0
B48: 2.2.4 | C48: Fundações Superficiais | M48: =ROUND(L48*K48,2) -> 0
B49: 2.2.5 | C49: Vigas, Baldrames e Alavancas | M49: =ROUND(L49*K49,2) -> 0
B50: 2.2.6 | M50: =ROUND(L50*K50,2) -> 0
B51: 2.2.7 | M51: =ROUND(L51*K51,2) -> 0
B52: 2.2.8 | M52: =ROUND(L52*K52,2) -> 0
B54: 2.3 | C54: Contenções / arrimos especiais
B55: 2.3.1 | M55: =ROUND(L55*K55,2) -> 0
B56: 2.3.2 | M56: =ROUND(L56*K56,2) -> 0
B57: 2.3.3 | M57: =ROUND(L57*K57,2) -> 0
B58: 2.3.4 | M58: =ROUND(L58*K58,2) -> 0
B59: 2.3.5 | M59: =ROUND(L59*K59,2) -> 0
B60: 2.3.6 | M60: =ROUND(L60*K60,2) -> 0
B61: 2.3.7 | M61: =ROUND(L61*K61,2) -> 0
C62: CUSTO TOTAL DO ITEM | M62: =SUM(M33:M61) -> 0 | N62: =IF($M$430=0,0,M62/$M$430) -> 0
B64: 3 | C64: SUPRAESTRUTURA
B65: 3.1 | C65: Concreto Armado | M65: =ROUND(L65*K65,2) -> 0
B66: 3.2 | C66: Pré-moldados | M66: =ROUND(L66*K66,2) -> 0
B67: 3.3 | M67: =ROUND(L67*K67,2) -> 0
B68: 3.4 | M68: =ROUND(L68*K68,2) -> 0
B69: 3.5 | M69: =ROUND(L69*K69,2) -> 0
C70: CUSTO TOTAL DO ITEM | M70: =SUM(M64:M69) -> 0 | N70: =IF($M$430=0,0,M70/$M$430) -> 0
B72: 4 | C72: PAREDES E PAINÉIS
B73: 4.1 | C73: Alvenarias
B74: 4.1.1 | C74: Tijolo furado | M74: =ROUND(L74*K74,2) -> 0
B75: 4.1.2 | C75: Tijolo maciço | M75: =ROUND(L75*K75,2) -> 0
B76: 4.1.3 | C76: Bloco estrutural | M76: =ROUND(L76*K76,2) -> 0
B77: 4.1.4 | C77: Paredes de Concreto | M77: =ROUND(L77*K77,2) -> 0
B78: 4.1.5 | C78: Vergas de Concreto | M78: =ROUND(L78*K78,2) -> 0
B79: 4.1.6 | C79: Arremates e Cunhas | M79: =ROUND(L79*K79,2) -> 0
B80: 4.1.7 | M80: =ROUND(L80*K80,2) -> 0
B81: 4.1.8 | M81: =ROUND(L81*K81,2) -> 0
B83: 4.2 | C83: Esquadrias de alumínio
B84: 4.2.1 | C84: Janelas | M84: =ROUND(L84*K84,2) -> 0
B85: 4.2.2 | C85: Portas | M85: =ROUND(L85*K85,2) -> 0
B86: 4.2.3 | C86: Basculantes | M86: =ROUND(L86*K86,2) -> 0
B87: 4.2.4 | C87: Gradis | M87: =ROUND(L87*K87,2) -> 0
B88: 4.2.5 | C88: Portões | M88: =ROUND(L88*K88,2) -> 0
B89: 4.2.6 | M89: =ROUND(L89*K89,2) -> 0
B90: 4.2.7 | M90: =ROUND(L90*K90,2) -> 0
B92: 4.3 | C92: Esquadrias de ferro
B93: 4.3.1 | C93: Janelas | M93: =ROUND(L93*K93,2) -> 0
B94: 4.3.2 | C94: Portas | M94: =ROUND(L94*K94,2) -> 0
B95: 4.3.3 | C95: Basculantes | M95: =ROUND(L95*K95,2) -> 0
B96: 4.3.4 | C96: Gradis | M96: =ROUND(L96*K96,2) -> 0
B97: 4.3.5 | C97: Portões | M97: =ROUND(L97*K97,2) -> 0
B98: 4.3.6 | C98: Porta corta-fogo | M98: =ROUND(L98*K98,2) -> 0
B99: 4.3.7 | C99: Escada Marinheiro | M99: =ROUND(L99*K99,2) -> 0
B100: 4.3.8 | C100: Alçapão | M100: =ROUND(L100*K100,2) -> 0
B101: 4.3.9 | M101: =ROUND(L101*K101,2) -> 0
B102: 4.3.10 | M102: =ROUND(L102*K102,2) -> 0
B104: 4.4 | C104: Esquadrias de madeira
B105: 4.4.1 | C105: Porta entrada 80x210cm | M105: =ROUND(L105*K105,2) -> 0
B106: 4.4.2 | C106: Portas internas 80x210cm | M106: =ROUND(L106*K106,2) -> 0
B107: 4.4.3 | C107: Portas internas 70x210cm | M107: =ROUND(L107*K107,2) -> 0
B108: 4.4.4 | C108: Portas internas 60x210cm | M108: =ROUND(L108*K108,2) -> 0
B109: 4.4.5 | C109: Batentes | M109: =ROUND(L109*K109,2) -> 0
B110: 4.4.6 | C110: Guarnições/alizares | M110: =ROUND(L110*K110,2) -> 0
B111: 4.4.7 | C111: Janelas | M111: =ROUND(L111*K111,2) -> 0
B112: 4.4.8 | M112: =ROUND(L112*K112,2) -> 0
B113: 4.4.9 | M113: =ROUND(L113*K113,2) -> 0
B115: 4.5 | C115: Ferragens
B116: 4.5.1 | C116: Conj. para porta social | M116: =ROUND(L116*K116,2) -> 0
B117: 4.5.2 | C117: Conj. para porta de serviço | M117: =ROUND(L117*K117,2) -> 0
B118: 4.5.3 | C118: Conj. para porta interna | M118: =ROUND(L118*K118,2) -> 0
B119: 4.5.4 | C119: Conj. para porta banheiro | M119: =ROUND(L119*K119,2) -> 0
B120: 4.5.5 | C120: Conj. porta de garagem | M120: =ROUND(L120*K120,2) -> 0
...

Sheet Orç_eventos_Infra
A1: (escolha) | L1: Grau de sigilo
A2: Habitacional horizontal | E2: Orçamento por Eventos da Infraestrutura | L2: #EXTERNO.CONFIDENCIAL
A3: Vertical: habit. / salas / misto
A4: Vertical andar livre | E4: =FRE!$D$4 -> Programa: | F4: =FRE!$E$4 -> Apoio à Produção de Imóveis - Pessoa Jurídica
A5: Vertical parede de concreto
J17: Unidade | K17: Quantidade | L17: Custo unitário | M17: Custo total | N17: % do item
B18: 1 | C18: TERRAPLENAGEM
B19: 1.1 | C19: ESTUDO DO SOLO (SONDAGEM, ENSAIOS, CONTROLE TECNOLÓGICO) | J19: vb | M19: =L19*K19 -> 0
B20: 1.2 | C20: TERRAPLENAGEM (CORTE E ATERRO) | J20: m3 | M20: =L20*K20 -> 0
B21: 1.3 | C21: PROTEÇÃO DE TALUDES (GRAMA, HIDROSSEMEADURA, ETC) | J21: m2 | M21: =L21*K21 -> 0
B22: 1.4 | M22: =L22*K22 -> 0
B23: 1.5 | M23: =L23*K23 -> 0
C24: CUSTO TOTAL DO ITEM | M24: =SUM(M18:M23) -> 0 | N24: =IF($M$91=0,0,M24/$M$91) -> 0
B26: 2 | C26: ÁGUA POTÁVEL
B27: 2.1 | C27: CAPTAÇÃO (EM REDE EXISTENTE, POÇO PROFUNDO, MANANCIAL, ETC) | M27: =L27*K27 -> 0
B28: 2.2 | C28: RESERVAÇÃO | J28: m3 | M28: =L28*K28 -> 0
B29: 2.3 | C29: REDE DE DISTRIBUIÇÃO DE ÁGUA | J29: m | M29: =L29*K29 -> 0
B30: 2.4 | C30: TRATAMENTO DA ÁGUA | J30: m3/s | M30: =L30*K30 -> 0
B31: 2.5 | M31: =L31*K31 -> 0
B32: 2.6 | M32: =L32*K32 -> 0
C33: CUSTO TOTAL DO ITEM | M33: =SUM(M26:M32) -> 0 | N33: =IF($M$91=0,0,M33/$M$91) -> 0
B35: 3 | C35: ESGOTO SANITÁRIO
B36: 3.1 | C36: REDE DE ESGOTAMENTO SANITÁRIO | J36: m | M36: =L36*K36 -> 0
B37: 3.2 | C37: ELEVATÓRIA | J37: m3/s | M37: =L37*K37 -> 0
B38: 3.3 | C38: TRATAMENTO DE EFLUENTES (FOSSA, SUMIDOURO, FILTRO, ETE) | J38: m3/s | M38: =L38*K38 -> 0
B39: 3.4 | M39: =L39*K39 -> 0
B40: 3.5 | M40: =L40*K40 -> 0
C41: CUSTO TOTAL DO ITEM | M41: =SUM(M35:M40) -> 0 | N41: =IF($M$91=0,0,M41/$M$91) -> 0
B43: 4 | C43: DRENAGEM DAS ÁGUAS PLUVIAIS
B44: 4.1 | C44: REDE DE DRENAGEM PLUVIAL | J44: m | M44: =L44*K44 -> 0
B45: 4.5 | C45: TERMINAL DE LANÇAMENTO | J45: und | M45: =L45*K45 -> 0
B46: 4.6 | M46: =L46*K46 -> 0
B47: 4.7 | M47: =L47*K47 -> 0
C48: CUSTO TOTAL DO ITEM | M48: =SUM(M43:M47) -> 0 | N48: =IF($M$91=0,0,M48/$M$91) -> 0
B50: 5 | C50: PAVIMENTAÇÃO
B51: 5.1 | C51: PAVIMENTAÇÃO EM | J51: m2 | M51: =L51*K51 -> 0
B52: 5.2 | C52: GUIAS E SARJETAS | J52: m | M52: =L52*K52 -> 0
B53: 5.3 | C53: PASSEIOS/CALÇADAS | J53: m2 | M53: =L53*K53 -> 0
B54: 5.4 | M54: =L54*K54 -> 0
B55: 5.5 | M55: =L55*K55 -> 0
C56: CUSTO TOTAL DO ITEM | M56: =SUM(M50:M55) -> 0 | N56: =IF($M$91=0,0,M56/$M$91) -> 0
B58: 6 | C58: ENERGIA E ILUMINAÇÃO
B59: 6.1 | C59: REDE DE ENERGIA | J59: m | M59: =L59*K59 -> 0
B60: 6.2 | C60: ILUMINAÇÃO PÚBLICA | J60: m | M60: =L60*K60 -> 0
B61: 6.3 | M61: =L61*K61 -> 0
B62: 6.4 | M62: =L62*K62 -> 0
C63: CUSTO TOTAL DO ITEM | M63: =SUM(M58:M62) -> 0 | N63: =IF($M$91=0,0,M63/$M$91) -> 0
B65: 7 | C65: TELEFONE
B66: 7.1 | C66: DUTOS | J66: m | M66: =L66*K66 -> 0
B67: 7.2 | C67: CABEAMENTOS | J67: m | M67: =L67*K67 -> 0
B68: 7.3 | M68: =L68*K68 -> 0
B69: 7.4 | M69: =L69*K69 -> 0
C70: CUSTO TOTAL DO ITEM | M70: =SUM(M65:M69) -> 0 | N70: =IF($M$91=0,0,M70/$M$91) -> 0
B72: 8 | C72: GÁS
B73: 8.1 | C73: REDE DE DISTRIBUIÇÃO | J73: m | M73: =L73*K73 -> 0
B74: 8.2 | C74: CENTRAL | J74: und | M74: =L74*K74 -> 0
B75: 8.3 | M75: =L75*K75 -> 0
B76: 8.4 | M76: =L76*K76 -> 0
C77: CUSTO TOTAL DO ITEM | M77: =SUM(M72:M76) -> 0 | N77: =IF($M$91=0,0,M77/$M$91) -> 0
B79: 9 | C79: OBRAS ESPECIAIS
B80: 9.1 | C80: MURO DE ARRIMO EM | J80: m3 | M80: =L80*K80 -> 0
B81: 9.2 | M81: =L81*K81 -> 0
B82: 9.3 | M82: =L82*K82 -> 0
C83: CUSTO TOTAL DO ITEM | M83: =SUM(M79:M82) -> 0 | N83: =IF($M$91=0,0,M83/$M$91) -> 0
B85: 10 | C85: PAISAGISMO, EQUIPAMENTOS E AMBIENTAÇÃO
B86: 10.1 | C86: PAISAGISMO | M86: =L86*K86 -> 0
B87: 10.2 | M87: =L87*K87 -> 0
B88: 10.3 | M88: =L88*K88 -> 0
C89: CUSTO TOTAL DO ITEM | M89: =SUM(M85:M88) -> 0 | N89: =IF($M$91=0,0,M89/$M$91) -> 0
C91: CUSTO DIRETO DE CONSTRUÇÃO | M91: =SUM(M18:M90)/2 -> 0
C92: BDI
C93: CUSTO TOTAL DE CONSTRUÇÃO | M93: =M91*(1+M92) -> 0
J96: Assinatura do responsável técnico
J97: Nome: | K97: =IF(FRE!$B$22="","",FRE!$B$22) -> {RESPONSÁVEL TÉCNICO}
J98: CPF: | K98: =IF(FRE!$M$22="","",FRE!$M$22) -> {DOC. RESPONSÁVEL}
J99: CREA/CAU: | K99: =IF(FRE!$J$22="","",FRE!$J$22) -> {CREA}

Sheet Orç_analítico_Equipamen_Faixa_I
A1: (escolha) | M1: Grau de sigilo
A2: Habitacional horizontal | E2: Orçamento Analítico Equipamentos Comunitários e de Uso Comum | M2: #EXTERNO.CONFIDENCIAL
A3: Vertical: habit. / salas / misto
A4: Vertical andar livre | E4: =FRE!$D$4 -> Programa: | F4: =FRE!$E$4 -> Apoio à Produção de Imóveis - Pessoa Jurídica
A5: Vertical parede de concreto
J17: Unidade | K17: Quantidade | L17: Custo unitário | M17: Custo total | N17: % do item
B18: 1 | C18: SERVIÇOS PRELIMINARES E GERAIS
B19: 1.1 | C19: Serviços técnicos (levantamento topográfico, projetos,especificações, orç., cronograma) | M19: =L19*K19 -> 0
B20: 1.2 | C20: Despesas iniciais (cópias, licenças, taxas e impostos) | M20: =L20*K20 -> 0
B21: 1.3 | C21: Instalações provisórias (tapumes, barracão, água, luz, esgoto e placas) | M21: =L21*K21 -> 0
B22: 1.4 | C22: Máquinas e ferramentas (betoneira, vibrador, serra, bomba, carrinho, guincho) | M22: =L22*K22 -> 0
B23: 1.5 | C23: Consumos | M23: =L23*K23 -> 0
B24: 1.6 | C24: Limpeza da Obra | M24: =L24*K24 -> 0
B25: 1.7 | C25: Transportes | M25: =L25*K25 -> 0
B26: 1.8 | M26: =L26*K26 -> 0
B27: 1.9 | M27: =L27*K27 -> 0
B28: 1.10 | M28: =L28*K28 -> 0
C29: CUSTO TOTAL DO ITEM | M29: =SUM(M18:M28) -> 0 | N29: =IF($M$356=0,0,M29/$M$356) -> 0
B31: 2 | C31: FUNDAÇÕES E CONTENÇÕES
B32: 2.1 | C32: Trabalhos com terra
B33: 2.1.1 | C33: Demolições | M33: =L33*K33 -> 0
B34: 2.1.2 | C34: Limpeza do terreno | M34: =L34*K34 -> 0
B35: 2.1.3 | C35: Escavações mecânicas | M35: =L35*K35 -> 0
B36: 2.1.4 | C36: Escavaçoes manuais | M36: =L36*K36 -> 0
B37: 2.1.5 | C37: Aterro e apiloamento | M37: =L37*K37 -> 0
B38: 2.1.6 | C38: Locação da Obra | D38: Trabalhos em | M38: =L38*K38 -> 0
B39: 2.1.7 | C39: Desmonte em Rocha | M39: =L39*K39 -> 0
B40: 2.1.8 | M40: =L40*K40 -> 0
B41: 2.1.9 | M41: =L41*K41 -> 0
B43: 2.2 | C43: Fundações e outros serviços
B44: 2.2.1 | C44: Escoramento do Terreno vizinho | M44: =L44*K44 -> 0
B45: 2.2.2 | C45: Reb. Lençol Freático/Drenagem | M45: =L45*K45 -> 0
B46: 2.2.3 | C46: Fundações Profundas | M46: =L46*K46 -> 0
B47: 2.2.4 | C47: Fundações Superficiais | M47: =L47*K47 -> 0
B48: 2.2.5 | C48: Vigas, Baldrames e Alavancas | M48: =L48*K48 -> 0
B49: 2.2.6 | M49: =L49*K49 -> 0
B50: 2.2.7 | M50: =L50*K50 -> 0
C51: CUSTO TOTAL DO ITEM | M51: =SUM(M31:M50) -> 0 | N51: =IF($M$356=0,0,M51/$M$356) -> 0
B53: 3 | C53: SUPRAESTRUTURA
B54: 3.1 | C54: Concreto Armado | M54: =L54*K54 -> 0
B55: 3.2 | C55: Pré-moldados | M55: =L55*K55 -> 0
B56: 3.3 | M56: =L56*K56 -> 0
B57: 3.4 | M57: =L57*K57 -> 0
B58: 3.5 | M58: =L58*K58 -> 0
C59: CUSTO TOTAL DO ITEM | M59: =SUM(M53:M58) -> 0 | N59: =IF($M$356=0,0,M59/$M$356) -> 0
B61: 4 | C61: PAREDES E PAINÉIS
B62: 4.1 | C62: Alvenarias
B63: 4.1.1 | C63: Tijolo furado | M63: =L63*K63 -> 0
B64: 4.1.2 | C64: Tijolo maciço | M64: =L64*K64 -> 0
B65: 4.1.3 | C65: Bloco estrutural | M65: =L65*K65 -> 0
B66: 4.1.4 | C66: Paredes de Concreto | M66: =L66*K66 -> 0
B67: 4.1.5 | C67: Vergas de Concreto | M67: =L67*K67 -> 0
B68: 4.1.6 | C68: Arremates e Cunhas | M68: =L68*K68 -> 0
B69: 4.1.7 | M69: =L69*K69 -> 0
B71: 4.2 | C71: Esquadrias de alumínio
B72: 4.2.1 | C72: Janelas | M72: =L72*K72 -> 0
B73: 4.2.2 | C73: Portas | M73: =L73*K73 -> 0
B74: 4.2.3 | C74: Basculantes | M74: =L74*K74 -> 0
B75: 4.2.4 | C75: Gradis | M75: =L75*K75 -> 0
B76: 4.2.5 | C76: Portões | M76: =L76*K76 -> 0
B77: 4.2.6 | M77: =L77*K77 -> 0
B79: 4.3 | C79: Esquadrias de ferro
B80: 4.3.1 | C80: Janelas | M80: =L80*K80 -> 0
B81: 4.3.2 | C81: Portas | M81: =L81*K81 -> 0
B82: 4.3.3 | C82: Basculantes | M82: =L82*K82 -> 0
B83: 4.3.4 | C83: Gradis | M83: =L83*K83 -> 0
B84: 4.3.5 | C84: Portões | M84: =L84*K84 -> 0
B85: 4.3.6 | C85: Porta corta-fogo | M85: =L85*K85 -> 0
B86: 4.3.7 | C86: Escada Marinheiro | M86: =L86*K86 -> 0
B87: 4.3.8 | C87: Alçapão | M87: =L87*K87 -> 0
B88: 4.3.9 | M88: =L88*K88 -> 0
B90: 4.4 | C90: Esquadrias de madeira
B91: 4.4.1 | C91: Porta entrada 80x210cm | M91: =L91*K91 -> 0
B92: 4.4.2 | C92: Portas internas 80x210cm | M92: =L92*K92 -> 0
B93: 4.4.3 | C93: Portas internas 70x210cm | M93: =L93*K93 -> 0
B94: 4.4.4 | C94: Portas internas 60x210cm | M94: =L94*K94 -> 0
B95: 4.4.5 | C95: Batentes | M95: =L95*K95 -> 0
B96: 4.4.6 | C96: Guarnições/alizares | M96: =L96*K96 -> 0
B97: 4.4.7 | C97: Janelas | M97: =L97*K97 -> 0
B98: 4.4.8 | M98: =L98*K98 -> 0
B100: 4.5 | C100: Ferragens
B101: 4.5.1 | C101: Conj. para porta social | M101: =L101*K101 -> 0
B102: 4.5.2 | C102: Conj. para porta de serviço | M102: =L102*K102 -> 0
B103: 4.5.3 | C103: Conj. para porta interna | M103: =L103*K103 -> 0
B104: 4.5.4 | C104: Conj. para porta banheiro | M104: =L104*K104 -> 0
B105: 4.5.5 | C105: Conj. porta de garagem | M105: =L105*K105 -> 0
B106: 4.5.6 | C106: Dobradiças | M106: =L106*K106 -> 0
B107: 4.5.7 | M107: =L107*K107 -> 0
B109: 4.6 | C109: Vidros e plásticos
B110: 4.6.1 | C110: Lisos | M110: =L110*K110 -> 0
B111: 4.6.2 | C111: Fantasia | M111: =L111*K111 -> 0
B112: 4.6.3 | C112: Temperado/Laminado | M112: =L112*K112 -> 0
B113: 4.6.4 | C113: Tijolo de vidro | M113: =L113*K113 -> 0
B114: 4.6.5 | C114: Plásticos e Acrílicos | M114: =L114*K114 -> 0
B115: 4.6.6 | M115: =L115*K115 -> 0
C116: CUSTO TOTAL DO ITEM | M116: =SUM(M61:M115) -> 0 | N116: =IF($M$356=0,0,M116/$M$356) -> 0
B118: 5 | C118: COBERTURAS E PROTEÇÕES
B119: 5.1 | C119: Telhados
B120: 5.1.1 | C120: Estrutura para telhado | M120: =L120*K120 -> 0
B121: 5.1.2 | C121: Telhas | M121: =L121*K121 -> 0
...

Sheet Cronograma
A1: (escolha) | N1: Grau de sigilo
A2: cronograma inicial | E2: Cronograma físico-financeiro global | N2: #EXTERNO.CONFIDENCIAL
A3: reprogramação
A4: Vertical andar livre | E4: =FRE!$D$4 -> Programa: | F4: =FRE!$E$4 -> Apoio à Produção de Imóveis - Pessoa Jurídica
A5: Vertical parede de concreto
C17: Tipo do cronograma: | D17: cronograma inicial | H17: Data da contratação: | N17: Data da retirada da suspensiva:
B19: Custos | D19: =FRE!B186 -> Edificações | J19: =FRE!M187 -> 0 | L19: =IF(SUM($J$19:$K$21)=0,0,J19/SUM($J$19:$K$21)) -> 0
D20: =FRE!B189 -> Infraestrutura e urbanização | J20: =IF(FRE!$N$189="não",0,FRE!M190) -> 0 | L20: =IF(SUM($J$19:$K$21)=0,0,J20/SUM($J$19:$K$21)) -> 0
D21: =FRE!B192 -> Equipamentos comunitários | J21: =IF(FRE!$E$4=FRE!$A$7,FRE!M193,) -> 0 | L21: =IF(SUM($J$19:$K$21)=0,0,J21/SUM($J$19:$K$21)) -> 0
D23: Infraestrutura não incidente | J23: =SUM(J24:K26) -> 0 | L23: =IF($J$23=0,0,J23/$J$23) -> 0
D24: =IF(FRE!B209="","",FRE!B209) | J24: =FRE!G209 -> 0 | L24: =IF($J$23=0,0,J24/$J$23) -> 0
D25: =IF(FRE!B210="","",FRE!B210) | J25: =FRE!G210 -> 0 | L25: =IF($J$23=0,0,J25/$J$23) -> 0
D26: =IF(FRE!B211="","",FRE!B211) | J26: =FRE!G211 -> 0 | L26: =IF($J$23=0,0,J26/$J$23) -> 0
B27: =FRE!N189 -> não | C27: =FRE!E4 -> Apoio à Produção de Imóveis - Pessoa Jurídica | D27: =FRE!A6 -> Produção de Lotes Urbanizados - PRODULOTE - PJ | E27: =FRE!A7 -> PCVA - Recursos FAR
B28: Etapa | C28: =D19 -> Edificações | E28: =D20 -> Infraestrutura e urbanização | G28: =D21 -> Equipamentos comunitários | I28: Evolução física da obra | K28: Indique a etapa que terá habite-se e CND | M28: % de liberação financeira | O28: Infra não incidente
C29: % da etapa | D29: % acumulado | E29: % da etapa | F29: % acumulado | G29: % da etapa | H29: % acumulado | I29: % da etapa | J29: % acumulado | K29: Indique | L29: % acumulado | M29: % da etapa | N29: % acumulado | O29: % da etapa | P29: % acumulado
B30: Executado | C30: 0 | D30: =SUM(C$30:C30) -> 0 | F30: =SUM(E$30:E30) -> 0 | H30: =SUM(G$30:G30) -> 0 | I30: =IF(SUM($J$19:$K$21)=0,0,(C30*$J$19+E30*$J$20+G30*$J$21)/SUM($J$19:$K$21)) -> 0 | J30: =SUM(I$30:I30) -> 0 | L30: =IF(COUNTA($K$30:$K$78)=0,0,COUNTA($K$30:K30)/COUNTA($K$30:$K$78)) -> 0 | M30: =IF(L30>=100%,5%,IF(N29>=95%,0,IF(J30<=95%,I30,(I30-(J30-95%))))) -> 0 | N30: =IF(L30>=100%,J30,IF(J30>95%,95%,J30)) -> 0 | P30: =SUM(O$30:O30) -> 0
B31: 1 | C31: 0.0327 | D31: =SUM(C$30:C31) -> 0.0327 | F31: =SUM(E$30:E31) -> 0 | H31: =SUM(G$30:G31) -> 0 | I31: =IF(SUM($J$19:$K$21)=0,0,(C31*$J$19+E31*$J$20+G31*$J$21)/SUM($J$19:$K$21)) -> 0 | J31: =SUM(I$30:I31) -> 0 | L31: =IF(COUNTA($K$30:$K$78)=0,0,COUNTA($K$30:K31)/COUNTA($K$30:$K$78)) -> 0 | M31: =IF(L31>=100%,5%,IF(N30>=95%,0,IF(J31<=95%,I31,(I31-(J31-95%))))) -> 0 | N31: =IF(L31>=100%,J31,IF(J31>95%,95%,J31)) -> 0 | P31: =SUM(O$30:O31) -> 0
B32: 2 | C32: 0.0327 | D32: =SUM(C$30:C32) -> 0.0654 | F32: =SUM(E$30:E32) -> 0 | H32: =SUM(G$30:G32) -> 0 | I32: =IF(SUM($J$19:$K$21)=0,0,(C32*$J$19+E32*$J$20+G32*$J$21)/SUM($J$19:$K$21)) -> 0 | J32: =SUM(I$30:I32) -> 0 | L32: =IF(COUNTA($K$30:$K$78)=0,0,COUNTA($K$30:K32)/COUNTA($K$30:$K$78)) -> 0 | M32: =IF(L32>=100%,5%,IF(N31>=95%,0,IF(J32<=95%,I32,(I32-(J32-95%))))) -> 0 | N32: =IF(L32>=100%,J32,IF(J32>95%,95%,J32)) -> 0 | P32: =SUM(O$30:O32) -> 0
B33: 3 | C33: 0.0327 | D33: =SUM(C$30:C33) -> 0.0981 | F33: =SUM(E$30:E33) -> 0 | H33: =SUM(G$30:G33) -> 0 | I33: =IF(SUM($J$19:$K$21)=0,0,(C33*$J$19+E33*$J$20+G33*$J$21)/SUM($J$19:$K$21)) -> 0 | J33: =SUM(I$30:I33) -> 0 | L33: =IF(COUNTA($K$30:$K$78)=0,0,COUNTA($K$30:K33)/COUNTA($K$30:$K$78)) -> 0 | M33: =IF(L33>=100%,5%,IF(N32>=95%,0,IF(J33<=95%,I33,(I33-(J33-95%))))) -> 0 | N33: =IF(L33>=100%,J33,IF(J33>95%,95%,J33)) -> 0 | P33: =SUM(O$30:O33) -> 0
B34: 4 | C34: 0.0327 | D34: =SUM(C$30:C34) -> 0.1308 | F34: =SUM(E$30:E34) -> 0 | H34: =SUM(G$30:G34) -> 0 | I34: =IF(SUM($J$19:$K$21)=0,0,(C34*$J$19+E34*$J$20+G34*$J$21)/SUM($J$19:$K$21)) -> 0 | J34: =SUM(I$30:I34) -> 0 | L34: =IF(COUNTA($K$30:$K$78)=0,0,COUNTA($K$30:K34)/COUNTA($K$30:$K$78)) -> 0 | M34: =IF(L34>=100%,5%,IF(N33>=95%,0,IF(J34<=95%,I34,(I34-(J34-95%))))) -> 0 | N34: =IF(L34>=100%,J34,IF(J34>95%,95%,J34)) -> 0 | P34: =SUM(O$30:O34) -> 0
B35: 5 | C35: 0.0327 | D35: =SUM(C$30:C35) -> 0.1635 | F35: =SUM(E$30:E35) -> 0 | H35: =SUM(G$30:G35) -> 0 | I35: =IF(SUM($J$19:$K$21)=0,0,(C35*$J$19+E35*$J$20+G35*$J$21)/SUM($J$19:$K$21)) -> 0 | J35: =SUM(I$30:I35) -> 0 | L35: =IF(COUNTA($K$30:$K$78)=0,0,COUNTA($K$30:K35)/COUNTA($K$30:$K$78)) -> 0 | M35: =IF(L35>=100%,5%,IF(N34>=95%,0,IF(J35<=95%,I35,(I35-(J35-95%))))) -> 0 | N35: =IF(L35>=100%,J35,IF(J35>95%,95%,J35)) -> 0 | P35: =SUM(O$30:O35) -> 0
B36: 6 | C36: 0.0327 | D36: =SUM(C$30:C36) -> 0.1962 | F36: =SUM(E$30:E36) -> 0 | H36: =SUM(G$30:G36) -> 0 | I36: =IF(SUM($J$19:$K$21)=0,0,(C36*$J$19+E36*$J$20+G36*$J$21)/SUM($J$19:$K$21)) -> 0 | J36: =SUM(I$30:I36) -> 0 | L36: =IF(COUNTA($K$30:$K$78)=0,0,COUNTA($K$30:K36)/COUNTA($K$30:$K$78)) -> 0 | M36: =IF(L36>=100%,5%,IF(N35>=95%,0,IF(J36<=95%,I36,(I36-(J36-95%))))) -> 0 | N36: =IF(L36>=100%,J36,IF(J36>95%,95%,J36)) -> 0 | P36: =SUM(O$30:O36) -> 0
B37: 7 | C37: 0.0327 | D37: =SUM(C$30:C37) -> 0.2289 | F37: =SUM(E$30:E37) -> 0 | H37: =SUM(G$30:G37) -> 0 | I37: =IF(SUM($J$19:$K$21)=0,0,(C37*$J$19+E37*$J$20+G37*$J$21)/SUM($J$19:$K$21)) -> 0 | J37: =SUM(I$30:I37) -> 0 | L37: =IF(COUNTA($K$30:$K$78)=0,0,COUNTA($K$30:K37)/COUNTA($K$30:$K$78)) -> 0 | M37: =IF(L37>=100%,5%,IF(N36>=95%,0,IF(J37<=95%,I37,(I37-(J37-95%))))) -> 0 | N37: =IF(L37>=100%,J37,IF(J37>95%,95%,J37)) -> 0 | P37: =SUM(O$30:O37) -> 0
B38: 8 | C38: 0.0327 | D38: =SUM(C$30:C38) -> 0.2616 | F38: =SUM(E$30:E38) -> 0 | H38: =SUM(G$30:G38) -> 0 | I38: =IF(SUM($J$19:$K$21)=0,0,(C38*$J$19+E38*$J$20+G38*$J$21)/SUM($J$19:$K$21)) -> 0 | J38: =SUM(I$30:I38) -> 0 | L38: =IF(COUNTA($K$30:$K$78)=0,0,COUNTA($K$30:K38)/COUNTA($K$30:$K$78)) -> 0 | M38: =IF(L38>=100%,5%,IF(N37>=95%,0,IF(J38<=95%,I38,(I38-(J38-95%))))) -> 0 | N38: =IF(L38>=100%,J38,IF(J38>95%,95%,J38)) -> 0 | P38: =SUM(O$30:O38) -> 0
B39: 9 | C39: 0.0327 | D39: =SUM(C$30:C39) -> 0.2943 | F39: =SUM(E$30:E39) -> 0 | H39: =SUM(G$30:G39) -> 0 | I39: =IF(SUM($J$19:$K$21)=0,0,(C39*$J$19+E39*$J$20+G39*$J$21)/SUM($J$19:$K$21)) -> 0 | J39: =SUM(I$30:I39) -> 0 | L39: =IF(COUNTA($K$30:$K$78)=0,0,COUNTA($K$30:K39)/COUNTA($K$30:$K$78)) -> 0 | M39: =IF(L39>=100%,5%,IF(N38>=95%,0,IF(J39<=95%,I39,(I39-(J39-95%))))) -> 0 | N39: =IF(L39>=100%,J39,IF(J39>95%,95%,J39)) -> 0 | P39: =SUM(O$30:O39) -> 0
B40: 10 | C40: 0.0327 | D40: =SUM(C$30:C40) -> 0.327 | F40: =SUM(E$30:E40) -> 0 | H40: =SUM(G$30:G40) -> 0 | I40: =IF(SUM($J$19:$K$21)=0,0,(C40*$J$19+E40*$J$20+G40*$J$21)/SUM($J$19:$K$21)) -> 0 | J40: =SUM(I$30:I40) -> 0 | L40: =IF(COUNTA($K$30:$K$78)=0,0,COUNTA($K$30:K40)/COUNTA($K$30:$K$78)) -> 0 | M40: =IF(L40>=100%,5%,IF(N39>=95%,0,IF(J40<=95%,I40,(I40-(J40-95%))))) -> 0 | N40: =IF(L40>=100%,J40,IF(J40>95%,95%,J40)) -> 0 | P40: =SUM(O$30:O40) -> 0
B41: 11 | C41: 0.0327 | D41: =SUM(C$30:C41) -> 0.3597 | F41: =SUM(E$30:E41) -> 0 | H41: =SUM(G$30:G41) -> 0 | I41: =IF(SUM($J$19:$K$21)=0,0,(C41*$J$19+E41*$J$20+G41*$J$21)/SUM($J$19:$K$21)) -> 0 | J41: =SUM(I$30:I41) -> 0 | L41: =IF(COUNTA($K$30:$K$78)=0,0,COUNTA($K$30:K41)/COUNTA($K$30:$K$78)) -> 0 | M41: =IF(L41>=100%,5%,IF(N40>=95%,0,IF(J41<=95%,I41,(I41-(J41-95%))))) -> 0 | N41: =IF(L41>=100%,J41,IF(J41>95%,95%,J41)) -> 0 | P41: =SUM(O$30:O41) -> 0
B42: 12 | C42: 0.0327 | D42: =SUM(C$30:C42) -> 0.3924 | F42: =SUM(E$30:E42) -> 0 | H42: =SUM(G$30:G42) -> 0 | I42: =IF(SUM($J$19:$K$21)=0,0,(C42*$J$19+E42*$J$20+G42*$J$21)/SUM($J$19:$K$21)) -> 0 | J42: =SUM(I$30:I42) -> 0 | L42: =IF(COUNTA($K$30:$K$78)=0,0,COUNTA($K$30:K42)/COUNTA($K$30:$K$78)) -> 0 | M42: =IF(L42>=100%,5%,IF(N41>=95%,0,IF(J42<=95%,I42,(I42-(J42-95%))))) -> 0 | N42: =IF(L42>=100%,J42,IF(J42>95%,95%,J42)) -> 0 | P42: =SUM(O$30:O42) -> 0
... B58: 28 | C58: 0.0327 | D58: =SUM(C$30:C58) -> 0.9156 | F58: =SUM(E$30:E58) -> 0 | H58: =SUM(G$30:G58) -> 0 | I58: =IF(SUM($J$19:$K$21)=0,0,(C58*$J$19+E58*$J$20+G58*$J$21)/SUM($J$19:$K$21)) -> 0 | J58: =SUM(I$30:I58) -> 0 | L58: =IF(COUNTA($K$30:$K$78)=0,0,COUNTA($K$30:K58)/COUNTA($K$30:$K$78)) -> 0 | M58: =IF(L58>=100%,5%,IF(N57>=95%,0,IF(J58<=95%,I58,(I58-(J58-95%))))) -> 0 | N58: =IF(L58>=100%,J58,IF(J58>95%,95%,J58)) -> 0 | P58: =SUM(O$30:O58) -> 0
B59: 29 | C59: 0.0344 | D59: =SUM(C$30:C59) -> 0.95 | F59: =SUM(E$30:E59) -> 0 | H59: =SUM(G$30:G59) -> 0 | I59: =IF(SUM($J$19:$K$21)=0,0,(C59*$J$19+E59*$J$20+G59*$J$21)/SUM($J$19:$K$21)) -> 0 | J59: =SUM(I$30:I59) -> 0 | K59: HABITE-SE E CND | L59: =IF(COUNTA($K$30:$K$78)=0,0,COUNTA($K$30:K59)/COUNTA($K$30:$K$78)) -> 1 | M59: =IF(L59>=100%,5%,IF(N58>=95%,0,IF(J59<=95%,I59,(I59-(J59-95%))))) -> 0.05 | N59: =IF(L59>=100%,J59,IF(J59>95%,95%,J59)) -> 0 | P59: =SUM(O$30:O59) -> 0
B60: 30 | C60: 0.05 | D60: =SUM(C$30:C60) -> 1 | F60: =SUM(E$30:E60) -> 0 | H60: =SUM(G$30:G60) -> 0 | I60: =IF(SUM($J$19:$K$21)=0,0,(C60*$J$19+E60*$J$20+G60*$J$21)/SUM($J$19:$K$21)) -> 0 | J60: =SUM(I$30:I60) -> 0 | L60: =IF(COUNTA($K$30:$K$78)=0,0,COUNTA($K$30:K60)/COUNTA($K$30:$K$78)) -> 1 | M60: =IF(L60>=100%,5%,IF(N59>=95%,0,IF(J60<=95%,I60,(I60-(J60-95%))))) -> 0.05 | N60: =IF(L60>=100%,J60,IF(J60>95%,95%,J60)) -> 0 | P60: =SUM(O$30:O60) -> 0
B61: 31 | D61: =SUM(C$30:C61) -> 1 | F61: =SUM(E$30:E61) -> 0 | H61: =SUM(G$30:G61) -> 0 | I61: =IF(SUM($J$19:$K$21)=0,0,(C61*$J$19+E61*$J$20+G61*$J$21)/SUM($J$19:$K$21)) -> 0 | J61: =SUM(I$30:I61) -> 0 | L61: =IF(COUNTA($K$30:$K$78)=0,0,COUNTA($K$30:K61)/COUNTA($K$30:$K$78)) -> 1 | M61: =IF(L61>=100%,5%,IF(N60>=95%,0,IF(J61<=95%,I61,(I61-(J61-95%))))) -> 0.05 | N61: =IF(L61>=100%,J61,IF(J61>95%,95%,J61)) -> 0 | P61: =SUM(O$30:O61) -> 0
B62: 32 | D62: =SUM(C$30:C62) -> 1 | F62: =SUM(E$30:E62) -> 0 | H62: =SUM(G$30:G62) -> 0 | I62: =IF(SUM($J$19:$K$21)=0,0,(C62*$J$19+E62*$J$20+G62*$J$21)/SUM($J$19:$K$21)) -> 0 | J62: =SUM(I$30:I62) -> 0 | L62: =IF(COUNTA($K$30:$K$78)=0,0,COUNTA($K$30:K62)/COUNTA($K$30:$K$78)) -> 1 | M62: =IF(L62>=100%,5%,IF(N61>=95%,0,IF(J62<=95%,I62,(I62-(J62-95%))))) -> 0.05 | N62: =IF(L62>=100%,J62,IF(J62>95%,95%,J62)) -> 0 | P62: =SUM(O$30:O62) -> 0
B63: 33 | D63: =SUM(C$30:C63) -> 1 | F63: =SUM(E$30:E63) -> 0 | H63: =SUM(G$30:G63) -> 0 | I63: =IF(SUM($J$19:$K$21)=0,0,(C63*$J$19+E63*$J$20+G63*$J$21)/SUM($J$19:$K$21)) -> 0 | J63: =SUM(I$30:I63) -> 0 | L63: =IF(COUNTA($K$30:$K$78)=0,0,COUNTA($K$30:K63)/COUNTA($K$30:$K$78)) -> 1 | M63: =IF(L63>=100%,5%,IF(N62>=95%,0,IF(J63<=95%,I63,(I63-(J63-95%))))) -> 0.05 | N63: =IF(L63>=100%,J63,IF(J63>95%,95%,J63)) -> 0 | P63: =SUM(O$30:O63) -> 0
B64: 34 | D64: =SUM(C$30:C64) -> 1 | F64: =SUM(E$30:E64) -> 0 | H64: =SUM(G$30:G64) -> 0 | I64: =IF(SUM($J$19:$K$21)=0,0,(C64*$J$19+E64*$J$20+G64*$J$21)/SUM($J$19:$K$21)) -> 0 | J64: =SUM(I$30:I64) -> 0 | L64: =IF(COUNTA($K$30:$K$78)=0,0,COUNTA($K$30:K64)/COUNTA($K$30:$K$78)) -> 1 | M64: =IF(L64>=100%,5%,IF(N63>=95%,0,IF(J64<=95%,I64,(I64-(J64-95%))))) -> 0.05 | N64: =IF(L64>=100%,J64,IF(J64>95%,95%,J64)) -> 0 | P64: =SUM(O$30:O64) -> 0
B65: 35 | D65: =SUM(C$30:C65) -> 1 | F65: =SUM(E$30:E65) -> 0 | H65: =SUM(G$30:G65) -> 0 | I65: =IF(SUM($J$19:$K$21)=0,0,(C65*$J$19+E65*$J$20+G65*$J$21)/SUM($J$19:$K$21)) -> 0 | J65: =SUM(I$30:I65) -> 0 | L65: =IF(COUNTA($K$30:$K$78)=0,0,COUNTA($K$30:K65)/COUNTA($K$30:$K$78)) -> 1 | M65: =IF(L65>=100%,5%,IF(N64>=95%,0,IF(J65<=95%,I65,(I65-(J65-95%))))) -> 0.05 | N65: =IF(L65>=100%,J65,IF(J65>95%,95%,J65)) -> 0 | P65: =SUM(O$30:O65) -> 0
B66: 36 | D66: =SUM(C$30:C66) -> 1 | F66: =SUM(E$30:E66) -> 0 | H66: =SUM(G$30:G66) -> 0 | I66: =IF(SUM($J$19:$K$21)=0,0,(C66*$J$19+E66*$J$20+G66*$J$21)/SUM($J$19:$K$21)) -> 0 | J66: =SUM(I$30:I66) -> 0 | L66: =IF(COUNTA($K$30:$K$78)=0,0,COUNTA($K$30:K66)/COUNTA($K$30:$K$78)) -> 1 | M66: =IF(L66>=100%,5%,IF(N65>=95%,0,IF(J66<=95%,I66,(I66-(J66-95%))))) -> 0.05 | N66: =IF(L66>=100%,J66,IF(J66>95%,95%,J66)) -> 0 | P66: =SUM(O$30:O66) -> 0
B67: 37 | D67: =SUM(C$30:C67) -> 1 | F67: =SUM(E$30:E67) -> 0 | H67: =SUM(G$30:G67) -> 0 | I67: =IF(SUM($J$19:$K$21)=0,0,(C67*$J$19+E67*$J$20+G67*$J$21)/SUM($J$19:$K$21)) -> 0 | J67: =SUM(I$30:I67) -> 0 | L67: =IF(COUNTA($K$30:$K$78)=0,0,COUNTA($K$30:K67)/COUNTA($K$30:$K$78)) -> 1 | M67: =IF(L67>=100%,5%,IF(N66>=95%,0,IF(J67<=95%,I67,(I67-(J67-95%))))) -> 0.05 | N67: =IF(L67>=100%,J67,IF(J67>95%,95%,J67)) -> 0 | P67: =SUM(O$30:O67) -> 0
B68: 38 | D68: =SUM(C$30:C68) -> 1 | F68: =SUM(E$30:E68) -> 0 | H68: =SUM(G$30:G68) -> 0 | I68: =IF(SUM($J$19:$K$21)=0,0,(C68*$J$19+E68*$J$20+G68*$J$21)/SUM($J$19:$K$21)) -> 0 | J68: =SUM(I$30:I68) -> 0 | L68: =IF(COUNTA($K$30:$K$78)=0,0,COUNTA($K$30:K68)/COUNTA($K$30:$K$78)) -> 1 | M68: =IF(L68>=100%,5%,IF(N67>=95%,0,IF(J68<=95%,I68,(I68-(J68-95%))))) -> 0.05 | N68: =IF(L68>=100%,J68,IF(J68>95%,95%,J68)) -> 0 | P68: =SUM(O$30:O68) -> 0
B69: 39 | D69: =SUM(C$30:C69) -> 1 | F69: =SUM(E$30:E69) -> 0 | H69: =SUM(G$30:G69) -> 0 | I69: =IF(SUM($J$19:$K$21)=0,0,(C69*$J$19+E69*$J$20+G69*$J$21)/SUM($J$19:$K$21)) -> 0 | J69: =SUM(I$30:I69) -> 0 | L69: =IF(COUNTA($K$30:$K$78)=0,0,COUNTA($K$30:K69)/COUNTA($K$30:$K$78)) -> 1 | M69: =IF(L69>=100%,5%,IF(N68>=95%,0,IF(J69<=95%,I69,(I69-(J69-95%))))) -> 0.05 | N69: =IF(L69>=100%,J69,IF(J69>95%,95%,J69)) -> 0 | P69: =SUM(O$30:O69) -> 0
B70: 40 | D70: =SUM(C$30:C70) -> 1 | F70: =SUM(E$30:E70) -> 0 | H70: =SUM(G$30:G70) -> 0 | I70: =IF(SUM($J$19:$K$21)=0,0,(C70*$J$19+E70*$J$20+G70*$J$21)/SUM($J$19:$K$21)) -> 0 | J70: =SUM(I$30:I70) -> 0 | L70: =IF(COUNTA($K$30:$K$78)=0,0,COUNTA($K$30:K70)/COUNTA($K$30:$K$78)) -> 1 | M70: =IF(L70>=100%,5%,IF(N69>=95%,0,IF(J70<=95%,I70,(I70-(J70-95%))))) -> 0.05 | N70: =IF(L70>=100%,J70,IF(J70>95%,95%,J70)) -> 0 | P70: =SUM(O$30:O70) -> 0
B71: 41 | D71: =SUM(C$30:C71) -> 1 | F71: =SUM(E$30:E71) -> 0 | H71: =SUM(G$30:G71) -> 0 | I71: =IF(SUM($J$19:$K$21)=0,0,(C71*$J$19+E71*$J$20+G71*$J$21)/SUM($J$19:$K$21)) -> 0 | J71: =SUM(I$30:I71) -> 0 | L71: =IF(COUNTA($K$30:$K$78)=0,0,COUNTA($K$30:K71)/COUNTA($K$30:$K$78)) -> 1 | M71: =IF(L71>=100%,5%,IF(N70>=95%,0,IF(J71<=95%,I71,(I71-(J71-95%))))) -> 0.05 | N71: =IF(L71>=100%,J71,IF(J71>95%,95%,J71)) -> 0 | P71: =SUM(O$30:O71) -> 0
B72: 42 | D72: =SUM(C$30:C72) -> 1 | F72: =SUM(E$30:E72) -> 0 | H72: =SUM(G$30:G72) -> 0 | I72: =IF(SUM($J$19:$K$21)=0,0,(C72*$J$19+E72*$J$20+G72*$J$21)/SUM($J$19:$K$21)) -> 0 | J72: =SUM(I$30:I72) -> 0 | L72: =IF(COUNTA($K$30:$K$78)=0,0,COUNTA($K$30:K72)/COUNTA($K$30:$K$78)) -> 1 | M72: =IF(L72>=100%,5%,IF(N71>=95%,0,IF(J72<=95%,I72,(I72-(J72-95%))))) -> 0.05 | N72: =IF(L72>=100%,J72,IF(J72>95%,95%,J72)) -> 0 | P72: =SUM(O$30:O72) -> 0
... B78: 48 | D78: =SUM(C$30:C78) -> 1 | F78: =SUM(E$30:E78) -> 0 | H78: =SUM(G$30:G78) -> 0 | I78: =IF(SUM($J$19:$K$21)=0,0,(C78*$J$19+E78*$J$20+G78*$J$21)/SUM($J$19:$K$21)) -> 0 | J78: =SUM(I$30:I78) -> 0 | L78: =IF(COUNTA($K$30:$K$78)=0,0,COUNTA($K$30:K78)/COUNTA($K$30:$K$78)) -> 1 | M78: =IF(L78>=100%,5%,IF(N77>=95%,0,IF(J78<=95%,I78,(I78-(J78-95%))))) -> 0.05 | N78: =IF(L78>=100%,J78,IF(J78>95%,95%,J78)) -> 0 | P78: =SUM(O$30:O78) -> 0
